Workbook

Sheet Balance 2018.12
A1: Language/ Sprache/ 言語/ Linguagem >>> | B1: English | C1: =MATCH(B1, H3:L3,0) -> 1
A3: E | B3: Measures | C3: =VLOOKUP(A3,[1]Sheet2!A:F,1+'[1]Balance 2021.12 '!C$1,FALSE) -> Amount in Group Crcy | H3: English | I3: Deutsch | J3: 日本語 | K3: Portugues | L3: 中文
A4: FS Item | B4: FS Item | C4: J10 | D4: J1R | E4: J20 | F4: J2R
A5: 111100 | B5: =VLOOKUP(A5,Sheet2!A:F,1+'Balance 2018.12'!C$1,FALSE) -> Cash on hand | C5: 17278224 | D5: 17278224 | E5: 24046108 | F5: 24046108
A6: 111200 | B6: =VLOOKUP(A6,Sheet2!A:F,1+'Balance 2018.12'!C$1,FALSE) -> Short-term deposits and other cash equivalents | C6: 8057775.2 | D6: 8057775.2 | E6: 11214008 | F6: 11214008
A7: 121100 | B7: =VLOOKUP(A7,Sheet2!A:F,1+'Balance 2018.12'!C$1,FALSE) -> Trade receivables, Gross | C7: 27016242 | D7: 27026921 | E7: 37598510 | F7: 37613371
A8: 121190 | B8: =VLOOKUP(A8,Sheet2!A:F,1+'Balance 2018.12'!C$1,FALSE) -> Trade receivables, Allowance | C8: -931550.74 | D8: -931550.74 | E8: -1296439.4 | F8: -1296439.4
A9: 121200 | B9: =VLOOKUP(A9,Sheet2!A:F,1+'Balance 2018.12'!C$1,FALSE) -> Receivables on disposal of PPE, Current, Gross | C9: 8519.82 | D9: 8519.82 | E9: 11857.03 | F9: 11857.03
A10: 121300 | B10: =VLOOKUP(A10,Sheet2!A:F,1+'Balance 2018.12'!C$1,FALSE) -> Receivables / disp. Intang.assets, Current, Gross | C10: 5679.88 | D10: 5679.88 | E10: 7904.69 | F10: 7904.69
A11: 121400 | B11: =VLOOKUP(A11,Sheet2!A:F,1+'Balance 2018.12'!C$1,FALSE) -> Receivables / disp. invest. subsid, Current, Gross | C11: 1324.84 | D11: 1324.84 | E11: 1843.78 | F11: 1843.78
A12: 121500 | B12: =VLOOKUP(A12,Sheet2!A:F,1+'Balance 2018.12'!C$1,FALSE) -> Receivables / disp. Inv. oth entities, Current, GV | C12: 3974.51 | D12: 3974.51 | E12: 5531.33 | F12: 5531.33
A13: 121600 | B13: =VLOOKUP(A13,Sheet2!A:F,1+'Balance 2018.12'!C$1,FALSE) -> Receivables /disp. Inv. oth assets, Current, Gross | C13: 2839.94 | D13: 2839.94 | E13: 3952.35 | F13: 3952.35
A14: 121700 | B14: =VLOOKUP(A14,Sheet2!A:F,1+'Balance 2018.12'!C$1,FALSE) -> Dividends receivable | C14: 1500 | D14: 1500 | E14: 2087.55 | F14: 2087.55
A15: 121800 | B15: =VLOOKUP(A15,Sheet2!A:F,1+'Balance 2018.12'!C$1,FALSE) -> Other receivables, Current, Gross | C15: 678279.37 | D15: 678279.37 | E15: 943961.54 | F15: 943961.54
A16: 121900 | B16: =VLOOKUP(A16,Sheet2!A:F,1+'Balance 2018.12'!C$1,FALSE) -> Accrued interests on receivables | C16: 48278.95 | D16: 48278.95 | E16: 67189.82 | F16: 67189.82
... A164: 799000 | B164: =VLOOKUP(A164,Sheet2!A:F,1+'Balance 2018.12'!C$1,FALSE) -> Net income/loss | C164: 22090605 | D164: 22092426 | E164: 32497223 | F164: 32499901
A165: 13100D | B165: =VLOOKUP(A165,Sheet2!A:F,1+'Balance 2018.12'!C$1,FALSE) -> Clearing Account - Gross Margin B/S | C165: 0 | D165: 0 | E165: 0 | F165: 0
A166: 21100D | B166: =VLOOKUP(A166,Sheet2!A:F,1+'Balance 2018.12'!C$1,FALSE) -> Clearing account - Receivables/payables, Current | C166: 0 | D166: 0 | E166: 0 | F166: 0
A167: 21110D | B167: =VLOOKUP(A167,Sheet2!A:F,1+'Balance 2018.12'!C$1,FALSE) -> Clearing account - Trade Rec/Pay, Current | C167: 0 | D167: 0 | E167: 0 | F167: 0
A168: 21170D | B168: =VLOOKUP(A168,Sheet2!A:F,1+'Balance 2018.12'!C$1,FALSE) -> Clearing - Dividends rec/pay, Current | C168: 0 | D168: 0 | E168: 0 | F168: 0
A169: 22100D | B169: =VLOOKUP(A169,Sheet2!A:F,1+'Balance 2018.12'!C$1,FALSE) -> Clearing account - Financial assets/liab, Current | C169: 0 | D169: 0 | E169: 0 | F169: 0
A170: 28100D | B170: =VLOOKUP(A170,Sheet2!A:F,1+'Balance 2018.12'!C$1,FALSE) -> Clearing account - Receiv./payables, Non-current | C170: 0 | D170: 0 | E170: 0 | F170: 0
A171: 41200D | B171: =VLOOKUP(A171,Sheet2!A:F,1+'Balance 2018.12'!C$1,FALSE) -> Clearing account - Gross margin | C171: 0 | D171: 0 | E171: 0 | F171: 0
A172: 58000D | B172: =VLOOKUP(A172,Sheet2!A:F,1+'Balance 2018.12'!C$1,FALSE) -> Clearing account - Other operating | C172: 0 | D172: 0 | E172: 0.01 | F172: 0.01
A173: 65400D | B173: =VLOOKUP(A173,Sheet2!A:F,1+'Balance 2018.12'!C$1,FALSE) -> Clearing account - financial result | C173: 0 | D173: 0 | E173: -0.01 | F173: -0.01

Sheet Balance sheet 2018.12
A1: Language/ Sprache/ 言語/ Linguagem >>> | B1: English | C1: =MATCH(B1, H3:L3,0) -> 1
B3: Measures | C3: Sign-Adjusted Amount in Group Crcy | H3: English | I3: Deutsch | J3: 日本語 | K3: Portugues | L3: 中文
A4: FS Item | C4: J10 | D4: J1R | E4: J20 | F4: J2R
A5: 111100 | B5: =VLOOKUP(A5,Sheet2!A:F,1+'Balance sheet 2018.12'!C$1,FALSE) -> Cash on hand | C5: 17278224 | D5: 17278224 | E5: 24046108 | F5: 24046108
A6: 111200 | B6: =VLOOKUP(A6,Sheet2!A:F,1+'Balance sheet 2018.12'!C$1,FALSE) -> Short-term deposits and other cash equivalents | C6: 8057775.2 | D6: 8057775.2 | E6: 11214008 | F6: 11214008
A7: Y1/BS/T11100 | B7: =VLOOKUP(A7,Sheet2!A:F,1+'Balance sheet 2018.12'!C$1,FALSE) -> Cash and cash equivalents | C7: 25335999 | D7: 25335999 | E7: 35260116 | F7: 35260116
A8: 121100 | B8: =VLOOKUP(A8,Sheet2!A:F,1+'Balance sheet 2018.12'!C$1,FALSE) -> Trade receivables, Gross | C8: 27016242 | D8: 27026921 | E8: 37598510 | F8: 37613371
A9: 121190 | B9: =VLOOKUP(A9,Sheet2!A:F,1+'Balance sheet 2018.12'!C$1,FALSE) -> Trade receivables, Allowance | C9: -931550.74 | D9: -931550.74 | E9: -1296439.4 | F9: -1296439.4
A10: 121200 | B10: =VLOOKUP(A10,Sheet2!A:F,1+'Balance sheet 2018.12'!C$1,FALSE) -> Receivables on disposal of PPE, Current, Gross | C10: 8519.82 | D10: 8519.82 | E10: 11857.03 | F10: 11857.03
A11: 121300 | B11: =VLOOKUP(A11,Sheet2!A:F,1+'Balance sheet 2018.12'!C$1,FALSE) -> Receivables / disp. Intang.assets, Current, Gross | C11: 5679.88 | D11: 5679.88 | E11: 7904.69 | F11: 7904.69
A12: 121400 | B12: =VLOOKUP(A12,Sheet2!A:F,1+'Balance sheet 2018.12'!C$1,FALSE) -> Receivables / disp. invest. subsid, Current, Gross | C12: 1324.84 | D12: 1324.84 | E12: 1843.78 | F12: 1843.78
A13: 121500 | B13: =VLOOKUP(A13,Sheet2!A:F,1+'Balance sheet 2018.12'!C$1,FALSE) -> Receivables / disp. Inv. oth entities, Current, GV | C13: 3974.51 | D13: 3974.51 | E13: 5531.33 | F13: 5531.33
A14: 121600 | B14: =VLOOKUP(A14,Sheet2!A:F,1+'Balance sheet 2018.12'!C$1,FALSE) -> Receivables /disp. Inv. oth assets, Current, Gross | C14: 2839.94 | D14: 2839.94 | E14: 3952.35 | F14: 3952.35
A15: 121700 | B15: =VLOOKUP(A15,Sheet2!A:F,1+'Balance sheet 2018.12'!C$1,FALSE) -> Dividends receivable | C15: 1500 | D15: 1500 | E15: 2087.55 | F15: 2087.55
A16: 121800 | B16: =VLOOKUP(A16,Sheet2!A:F,1+'Balance sheet 2018.12'!C$1,FALSE) -> Other receivables, Current, Gross | C16: 678279.37 | D16: 678279.37 | E16: 943961.54 | F16: 943961.54
A17: 121900 | B17: =VLOOKUP(A17,Sheet2!A:F,1+'Balance sheet 2018.12'!C$1,FALSE) -> Accrued interests on receivables | C17: 48278.95 | D17: 48278.95 | E17: 67189.82 | F17: 67189.82
A18: 121990 | B18: =VLOOKUP(A18,Sheet2!A:F,1+'Balance sheet 2018.12'!C$1,FALSE) -> Other receivables, Allow | C18: -19879.57 | D18: -19879.57 | E18: -27666.4 | F18: -27666.4
A19: Y1/BS/T12100 | B19: =VLOOKUP(A19,Sheet2!A:F,1+'Balance sheet 2018.12'!C$1,FALSE) -> Trade and other current receivables | C19: 26815209 | D19: 26825888 | E19: 37318732 | F19: 37333594
A20: 123100 | B20: =VLOOKUP(A20,Sheet2!A:F,1+'Balance sheet 2018.12'!C$1,FALSE) -> Prepaid expenses | C20: 49494.5 | D20: 49494.5 | E20: 68881.51 | F20: 68881.51
A21: Y1/BS/T12300 | B21: =VLOOKUP(A21,Sheet2!A:F,1+'Balance sheet 2018.12'!C$1,FALSE) -> Other current assets | C21: 49494.5 | D21: 49494.5 | E21: 68881.51 | F21: 68881.51
A22: 131100 | B22: =VLOOKUP(A22,Sheet2!A:F,1+'Balance sheet 2018.12'!C$1,FALSE) -> Raw materials | C22: 2194399.5 | D22: 2194399.5 | E22: 3053946.2 | F22: 3053946.2
A23: 131200 | B23: =VLOOKUP(A23,Sheet2!A:F,1+'Balance sheet 2018.12'!C$1,FALSE) -> Merchandise | C23: 2568881.8 | D23: 2568881.8 | E23: 3575113.2 | F23: 3575113.2
A24: 131300 | B24: =VLOOKUP(A24,Sheet2!A:F,1+'Balance sheet 2018.12'!C$1,FALSE) -> Production supplies | C24: 2271.96 | D24: 2271.96 | E24: 3161.88 | F24: 3161.88
A25: 131400 | B25: =VLOOKUP(A25,Sheet2!A:F,1+'Balance sheet 2018.12'!C$1,FALSE) -> Work in progress | C25: 674933.05 | D25: 674933.05 | E25: 939304.45 | F25: 939304.45
A26: 131500 | B26: =VLOOKUP(A26,Sheet2!A:F,1+'Balance sheet 2018.12'!C$1,FALSE) -> Finished goods | C26: 685751.33 | D26: 685751.33 | E26: 954360.24 | F26: 954360.24
A27: 131600 | B27: =VLOOKUP(A27,Sheet2!A:F,1+'Balance sheet 2018.12'!C$1,FALSE) -> Other inventories | C27: 1419.98 | D27: 1419.98 | E27: 1976.17 | F27: 1976.17
A28: 13100D | B28: =VLOOKUP(A28,Sheet2!A:F,1+'Balance sheet 2018.12'!C$1,FALSE) -> Clearing Account - Gross Margin B/S | C28: 0 | D28: 0 | E28: 0 | F28: 0
A29: Y1/BS/T13100 | B29: =VLOOKUP(A29,Sheet2!A:F,1+'Balance sheet 2018.12'!C$1,FALSE) -> Inventories | C29: 6127657.6 | D29: 6127657.6 | E29: 8527862.1 | F29: 8527862.1
A30: 141100 | B30: =VLOOKUP(A30,Sheet2!A:F,1+'Balance sheet 2018.12'!C$1,FALSE) -> Other financial assets at FVTOCI, Current | C30: 20515.85 | D30: 20515.85 | E30: 28551.91 | F30: 28551.91
A31: 141200 | B31: =VLOOKUP(A31,Sheet2!A:F,1+'Balance sheet 2018.12'!C$1,FALSE) -> Derivatives, Current | C31: 10456 | D31: 10456 | E31: 14551.61 | F31: 14551.61
A32: 141300 | B32: =VLOOKUP(A32,Sheet2!A:F,1+'Balance sheet 2018.12'!C$1,FALSE) -> Financial assets at FVPL, Current | C32: 5711.86 | D32: 5711.86 | E32: 7949.2 | F32: 7949.2
A33: 141400 | B33: =VLOOKUP(A33,Sheet2!A:F,1+'Balance sheet 2018.12'!C$1,FALSE) -> Loans and cash advances, Current, Gross | C33: 31239.32 | D33: 31239.32 | E33: 43475.77 | F33: 43475.77
A34: 141490 | B34: =VLOOKUP(A34,Sheet2!A:F,1+'Balance sheet 2018.12'!C$1,FALSE) -> Loans and cash advances, Current, Allowance | C34: -8519.81 | D34: -8519.81 | E34: -11857.03 | F34: -11857.03
A35: Y1/BS/T14100 | B35: =VLOOKUP(A35,Sheet2!A:F,1+'Balance sheet 2018.12'!C$1,FALSE) -> Other current financial assets | C35: 59403.22 | D35: 59403.22 | E35: 82671.46 | F35: 82671.46
A36: Y1/BS/TAC100 | B36: =VLOOKUP(A36,Sheet2!A:F,1+'Balance sheet 2018.12'!C$1,FALSE) -> Current assets oth.than incl.in disposal groups | C36: 58387764 | D36: 58398442 | E36: 81258263 | F36: 81273125
A37: 151100 | B37: =VLOOKUP(A37,Sheet2!A:F,1+'Balance sheet 2018.12'!C$1,FALSE) -> NC assets or disp. groups classified HFS | C37: 2000 | D37: 2000 | E37: 2783.4 | F37: 2783.4
A38: Y1/BS/TAC200 | B38: =VLOOKUP(A38,Sheet2!A:F,1+'Balance sheet 2018.12'!C$1,FALSE) -> NC assets or disp. groups classified HFS/HDO | C38: 2000 | D38: 2000 | E38: 2783.4 | F38: 2783.4
A39: Y1/BS/TAC000 | B39: =VLOOKUP(A39,Sheet2!A:F,1+'Balance sheet 2018.12'!C$1,FALSE) -> Current assets | C39: 58389764 | D39: 58400442 | E39: 81261046 | F39: 81275908
A40: 161100 | B40: =VLOOKUP(A40,Sheet2!A:F,1+'Balance sheet 2018.12'!C$1,FALSE) -> Lands and buildings | C40: 22252278 | D40: 22252278 | E40: 30968499 | F40: 30968499
A41: 161190 | B41: =VLOOKUP(A41,Sheet2!A:F,1+'Balance sheet 2018.12'!C$1,FALSE) -> Lands and buildings, Depreciation | C41: -7107184.5 | D41: -7107184.5 | E41: -9891070 | F41: -9891070
A42: 161200 | B42: =VLOOKUP(A42,Sheet2!A:F,1+'Balance sheet 2018.12'!C$1,FALSE) -> Tangibles assets under construction | C42: 1102669.8 | D42: 1102669.8 | E42: 1534585.8 | F42: 1534585.8
A43: 161300 | B43: =VLOOKUP(A43,Sheet2!A:F,1+'Balance sheet 2018.12'!C$1,FALSE) -> Office equipment | C43: 229332.65 | D43: 229332.65 | E43: 319162.32 | F43: 319162.32
A44: 161390 | B44: =VLOOKUP(A44,Sheet2!A:F,1+'Balance sheet 2018.12'!C$1,FALSE) -> Office equipment, Depreciation | C44: -73862.62 | D44: -73862.62 | E44: -102794.61 | F44: -102794.61
A45: 161400 | B45: =VLOOKUP(A45,Sheet2!A:F,1+'Balance sheet 2018.12'!C$1,FALSE) -> Vehicles | C45: 73838.39 | D45: 73838.39 | E45: 102760.91 | F45: 102760.91
A46: 161490 | B46: =VLOOKUP(A46,Sheet2!A:F,1+'Balance sheet 2018.12'!C$1,FALSE) -> Vehicles, Depreciation | C46: -51118.89 | D46: -51118.89 | E46: -71142.17 | F46: -71142.17
A47: 161500 | B47: =VLOOKUP(A47,Sheet2!A:F,1+'Balance sheet 2018.12'!C$1,FALSE) -> Machinery | C47: 50550.89 | D47: 50550.89 | E47: 70351.71 | F47: 70351.71
A48: 161590 | B48: =VLOOKUP(A48,Sheet2!A:F,1+'Balance sheet 2018.12'!C$1,FALSE) -> Machinery, Depreciation | C48: -21469.92 | D48: -21469.92 | E48: -29879.71 | F48: -29879.71
A49: 161600 | B49: =VLOOKUP(A49,Sheet2!A:F,1+'Balance sheet 2018.12'!C$1,FALSE) -> Other property, plant and equipment | C49: 631650.43 | D49: 631650.43 | E49: 879068.05 | F49: 879068.05
A50: 161690 | B50: =VLOOKUP(A50,Sheet2!A:F,1+'Balance sheet 2018.12'!C$1,FALSE) -> Other property, plant and equipment, Depreciation | C50: -410371.02 | D50: -410371.02 | E50: -571113.5 | F50: -571113.5
A51: Y1/BS/T16100 | B51: =VLOOKUP(A51,Sheet2!A:F,1+'Balance sheet 2018.12'!C$1,FALSE) -> Property, plant and equipment | C51: 16676313 | D51: 16676313 | E51: 23208428 | F51: 23208428
A52: 162100 | B52: =VLOOKUP(A52,Sheet2!A:F,1+'Balance sheet 2018.12'!C$1,FALSE) -> Investment property | C52: 108485.62 | D52: 108485.62 | E52: 150979.48 | F52: 150979.48
A53: 162190 | B53: =VLOOKUP(A53,Sheet2!A:F,1+'Balance sheet 2018.12'!C$1,FALSE) -> Investment property, Depreciation | C53: -18033.6 | D53: -18033.6 | E53: -25097.39 | F53: -25097.39
A54: Y1/BS/T16200 | B54: =VLOOKUP(A54,Sheet2!A:F,1+'Balance sheet 2018.12'!C$1,FALSE) -> Investment property | C54: 90452.02 | D54: 90452.02 | E54: 125882.09 | F54: 125882.09
A55: 163100 | B55: =VLOOKUP(A55,Sheet2!A:F,1+'Balance sheet 2018.12'!C$1,FALSE) -> Goodwill | C55: 356634.74 | D55: 356634.74 | E55: 496330.93 | F55: 496330.93
A56: Y1/BS/T16300 | B56: =VLOOKUP(A56,Sheet2!A:F,1+'Balance sheet 2018.12'!C$1,FALSE) -> Goodwill | C56: 356634.74 | D56: 356634.74 | E56: 496330.93 | F56: 496330.93
A57: 164100 | B57: =VLOOKUP(A57,Sheet2!A:F,1+'Balance sheet 2018.12'!C$1,FALSE) -> Brand names | C57: 494206.16 | D57: 494206.16 | E57: 687786.8 | F57: 687786.8
A58: 164190 | B58: =VLOOKUP(A58,Sheet2!A:F,1+'Balance sheet 2018.12'!C$1,FALSE) -> Brand names, Amortization | C58: -13460.86 | D58: -13460.86 | E58: -18733.5 | F58: -18733.5
A59: 164200 | B59: =VLOOKUP(A59,Sheet2!A:F,1+'Balance sheet 2018.12'!C$1,FALSE) -> Computer software | C59: 6692624.1 | D59: 6692624.1 | E59: 9314126.2 | F59: 9314126.2
A60: 164290 | B60: =VLOOKUP(A60,Sheet2!A:F,1+'Balance sheet 2018.12'!C$1,FALSE) -> Computer software, Amortization | C60: -3170078.9 | D60: -3170078.9 | E60: -4411799.5 | F60: -4411799.5
A61: 164300 | B61: =VLOOKUP(A61,Sheet2!A:F,1+'Balance sheet 2018.12'!C$1,FALSE) -> Patents, trademarks and other rights | C61: 937179.49 | D61: 937179.49 | E61: 1304273 | F61: 1304273
A62: 164390 | B62: =VLOOKUP(A62,Sheet2!A:F,1+'Balance sheet 2018.12'!C$1,FALSE) -> Patents, trademarks and other rights, Amortization | C62: -615698.53 | D62: -615698.53 | E62: -856867.86 | F62: -856867.86
A63: 164400 | B63: =VLOOKUP(A63,Sheet2!A:F,1+'Balance sheet 2018.12'!C$1,FALSE) -> Intangible assets under development | C63: 67306.52 | D63: 67306.52 | E63: 93670.53 | F63: 93670.53
A64: 164490 | B64: =VLOOKUP(A64,Sheet2!A:F,1+'Balance sheet 2018.12'!C$1,FALSE) -> Intangible assets under development, Impairment | C64: -22719.51 | D64: -22719.51 | E64: -31618.75 | F64: -31618.75
A65: 164500 | B65: =VLOOKUP(A65,Sheet2!A:F,1+'Balance sheet 2018.12'!C$1,FALSE) -> Other intangible assets | C65: 21938.01 | D65: 21938.01 | E65: 30531.14 | F65: 30531.14
A66: 164590 | B66: =VLOOKUP(A66,Sheet2!A:F,1+'Balance sheet 2018.12'!C$1,FALSE) -> Other intangible assets, Amortization | C66: -10996.84 | D66: -10996.84 | E66: -15304.32 | F66: -15304.32
A67: Y1/BS/T16400 | B67: =VLOOKUP(A67,Sheet2!A:F,1+'Balance sheet 2018.12'!C$1,FALSE) -> Intangible assets | C67: 4380299.6 | D67: 4380299.6 | E67: 6096063.9 | F67: 6096063.9
A68: 171000 | B68: =VLOOKUP(A68,Sheet2!A:F,1+'Balance sheet 2018.12'!C$1,FALSE) -> Investments accounted for using equity method | C68: 44488.08 | D68: 43188.08 | E68: 58758.08 | F68: 56948.87
A69: Y1/BS/T17100 | B69: =VLOOKUP(A69,Sheet2!A:F,1+'Balance sheet 2018.12'!C$1,FALSE) -> Investments accounted for using equity method | C69: 44488.08 | D69: 43188.08 | E69: 58758.08 | F69: 56948.87
A70: 172100 | B70: =VLOOKUP(A70,Sheet2!A:F,1+'Balance sheet 2018.12'!C$1,FALSE) -> Investments in subs, JV and associates, GV | C70: 39999.96 | D70: 39999.96 | E70: 58823.94 | F70: 58823.94
A71: 172190 | B71: =VLOOKUP(A71,Sheet2!A:F,1+'Balance sheet 2018.12'!C$1,FALSE) -> Investments in subs, JV and associates, Impair | C71: 0 | D71: 0 | E71: 0 | F71: 0
A72: 172200 | B72: =VLOOKUP(A72,Sheet2!A:F,1+'Balance sheet 2018.12'!C$1,FALSE) -> Other financial assets at FVTOCI, Non-current | C72: 6171.5 | D72: 6171.5 | E72: 8588.88 | F72: 8588.88
A73: 172400 | B73: =VLOOKUP(A73,Sheet2!A:F,1+'Balance sheet 2018.12'!C$1,FALSE) -> Financial assets at FVPL, Non-current | C73: 1811.89 | D73: 1811.89 | E73: 2521.61 | F73: 2521.61
A74: Y1/BS/T17200 | B74: =VLOOKUP(A74,Sheet2!A:F,1+'Balance sheet 2018.12'!C$1,FALSE) -> Other non-current financial assets | C74: 47983.35 | D74: 47983.35 | E74: 69934.43 | F74: 69934.43
A75: 181100 | B75: =VLOOKUP(A75,Sheet2!A:F,1+'Balance sheet 2018.12'!C$1,FALSE) -> Loans and cash advances, Non-current, Gross | C75: 289141.84 | D75: 289141.84 | E75: 402398.78 | F75: 402398.78
A76: 181190 | B76: =VLOOKUP(A76,Sheet2!A:F,1+'Balance sheet 2018.12'!C$1,FALSE) -> Loans and cash advances, Non-current, Allowance | C76: -14199.68 | D76: -14199.68 | E76: -19761.71 | F76: -19761.71
A77: 181200 | B77: =VLOOKUP(A77,Sheet2!A:F,1+'Balance sheet 2018.12'!C$1,FALSE) -> Receivables on disposal of PPE, N-Current, Gross | C77: 8519.81 | D77: 8519.81 | E77: 11857.03 | F77: 11857.03
A78: 181300 | B78: =VLOOKUP(A78,Sheet2!A:F,1+'Balance sheet 2018.12'!C$1,FALSE) -> Receiv./ disp. Intang.assets, N-Current, Gross | C78: 2839.94 | D78: 2839.94 | E78: 3952.35 | F78: 3952.35
A79: 181400 | B79: =VLOOKUP(A79,Sheet2!A:F,1+'Balance sheet 2018.12'!C$1,FALSE) -> Receiv./ disp. invest. subsid, N-Current, Gross | C79: 12000 | D79: 12000 | E79: 16700.4 | F79: 16700.4
A80: 181500 | B80: =VLOOKUP(A80,Sheet2!A:F,1+'Balance sheet 2018.12'!C$1,FALSE) -> Receiv. / disp. Inv. oth entities, N-Current, GV | C80: 3000 | D80: 3000 | E80: 4175.1 | F80: 4175.1
A81: 181600 | B81: =VLOOKUP(A81,Sheet2!A:F,1+'Balance sheet 2018.12'!C$1,FALSE) -> Receiv. /disp. Inv. oth assets, N-Current, Gross | C81: 2839.95 | D81: 2839.95 | E81: 3952.35 | F81: 3952.35
A82: 181800 | B82: =VLOOKUP(A82,Sheet2!A:F,1+'Balance sheet 2018.12'!C$1,FALSE) -> Other receivables, Non-current, Gross | C82: 210155.4 | D82: 210155.4 | E82: 292473.34 | F82: 292473.34
A83: 181890 | B83: =VLOOKUP(A83,Sheet2!A:F,1+'Balance sheet 2018.12'!C$1,FALSE) -> Receivables, Non-current, Allowance | C83: -28399.38 | D83: -28399.38 | E83: -39523.42 | F83: -39523.42
A84: Y1/BS/T18100 | B84: =VLOOKUP(A84,Sheet2!A:F,1+'Balance sheet 2018.12'!C$1,FALSE) -> Non-current receivables | C84: 485897.88 | D84: 485897.88 | E84: 676224.22 | F84: 676224.22
A85: 182100 | B85: =VLOOKUP(A85,Sheet2!A:F,1+'Balance sheet 2018.12'!C$1,FALSE) -> Deferred tax assets | C85: 0 | D85: 0 | E85: 0 | F85: 0
A86: Y1/BS/T18200 | B86: =VLOOKUP(A86,Sheet2!A:F,1+'Balance sheet 2018.12'!C$1,FALSE) -> Deferred tax assets | C86: 0 | D86: 0 | E86: 0 | F86: 0
A87: Y1/BS/TANC00 | B87: =VLOOKUP(A87,Sheet2!A:F,1+'Balance sheet 2018.12'!C$1,FALSE) -> Non Current assets | C87: 22082069 | D87: 22080769 | E87: 30731621 | F87: 30729812
A88: Y1/BS/TA0000 | B88: =VLOOKUP(A88,Sheet2!A:F,1+'Balance sheet 2018.12'!C$1,FALSE) -> Assets | C88: 80471833 | D88: 80481211 | E88: 1.1199267e+08 | F88: 1.1200572e+08
A89: 211100 | B89: =VLOOKUP(A89,Sheet2!A:F,1+'Balance sheet 2018.12'!C$1,FALSE) -> Trade payables | C89: 16422293 | D89: 16422293 | E89: 22854908 | F89: 22854908
A90: 21110D | B90: =VLOOKUP(A90,Sheet2!A:F,1+'Balance sheet 2018.12'!C$1,FALSE) -> Clearing account - Trade Rec/Pay, Current | C90: 0 | D90: 0 | E90: 0 | F90: 0
A91: 211200 | B91: =VLOOKUP(A91,Sheet2!A:F,1+'Balance sheet 2018.12'!C$1,FALSE) -> Debts on purchase of PPE, Current | C91: 1996.32 | D91: 1996.32 | E91: 2778.29 | F91: 2778.29
A92: 211300 | B92: =VLOOKUP(A92,Sheet2!A:F,1+'Balance sheet 2018.12'!C$1,FALSE) -> Debts on purchase of intangible assets, Current | C92: 4259.91 | D92: 4259.91 | E92: 5928.51 | F92: 5928.51
A93: 211400 | B93: =VLOOKUP(A93,Sheet2!A:F,1+'Balance sheet 2018.12'!C$1,FALSE) -> Debts on purchase of inv. in subs., Current | C93: 1500 | D93: 1500 | E93: 2087.56 | F93: 2087.56
A94: 211500 | B94: =VLOOKUP(A94,Sheet2!A:F,1+'Balance sheet 2018.12'!C$1,FALSE) -> Debts on purchase / inv. in oth. entities, Current | C94: 1500 | D94: 1500 | E94: 2087.56 | F94: 2087.56
A95: 211600 | B95: =VLOOKUP(A95,Sheet2!A:F,1+'Balance sheet 2018.12'!C$1,FALSE) -> Debts on purchase of inv / other assets, Current | C95: 1324.84 | D95: 1324.84 | E95: 1843.77 | F95: 1843.77
A96: 211700 | B96: =VLOOKUP(A96,Sheet2!A:F,1+'Balance sheet 2018.12'!C$1,FALSE) -> Dividends payable | C96: 3224.51 | D96: 3224.51 | E96: 4487.55 | F96: 4487.55
A97: 21170D | B97: =VLOOKUP(A97,Sheet2!A:F,1+'Balance sheet 2018.12'!C$1,FALSE) -> Clearing - Dividends rec/pay, Current | C97: 0 | D97: 0 | E97: 0 | F97: 0
A98: 211800 | B98: =VLOOKUP(A98,Sheet2!A:F,1+'Balance sheet 2018.12'!C$1,FALSE) -> Other payables, Current | C98: 217229.71 | D98: 217229.71 | E98: 302318.64 | F98: 302318.64
A99: 211900 | B99: =VLOOKUP(A99,Sheet2!A:F,1+'Balance sheet 2018.12'!C$1,FALSE) -> Accrued interests on financial liab./ payables | C99: 9087.8 | D99: 9087.8 | E99: 12647.49 | F99: 12647.49
A100: 21100D | B100: =VLOOKUP(A100,Sheet2!A:F,1+'Balance sheet 2018.12'!C$1,FALSE) -> Clearing account - Receivables/payables, Current | C100: 0 | D100: 0 | E100: 0 | F100: 0
A101: Y1/BS/T21100 | B101: =VLOOKUP(A101,Sheet2!A:F,1+'Balance sheet 2018.12'!C$1,FALSE) -> Trade and other current payables | C101: 16662416 | D101: 16662416 | E101: 23189087 | F101: 23189087
...

Sheet P&L 2018.12
A1: Language/ Sprache/ 言語/ Linguagem >>> | B1: English | C1: =MATCH(B1, H3:L3,0) -> 1
C3: Sign-Adjusted Amount in Group Crcy | D3: Sign-Adjusted Amount in Group Crcy | E3: Sign-Adjusted Amount in Group Crcy | F3: Sign-Adjusted Amount in Group Crcy | H3: English | I3: Deutsch | J3: 日本語 | K3: Portugues | L3: 中文
A4: FS Item | C4: J10 | D4: J1R | E4: J20 | F4: J2R
A5: 411100 | B5: =VLOOKUP(A5,Sheet2!A:F,1+'P&L 2018.12'!C$1,FALSE) -> Sale of goods | C5: 2.4917317e+08 | D5: 2.4917317e+08 | E5: 3.6643401e+08 | F5: 3.6643401e+08
A6: Y1/PL/T41100 | B6: =VLOOKUP(A6,Sheet2!A:F,1+'P&L 2018.12'!C$1,FALSE) -> Revenue | C6: 2.4917317e+08 | D6: 2.4917317e+08 | E6: 3.6643401e+08 | F6: 3.6643401e+08
A7: 412100 | B7: =VLOOKUP(A7,Sheet2!A:F,1+'P&L 2018.12'!C$1,FALSE) -> Changes in Inventory | C7: -10949723 | D7: -10949723 | E7: -16089373 | F7: -16089373
A8: 412200 | B8: =VLOOKUP(A8,Sheet2!A:F,1+'P&L 2018.12'!C$1,FALSE) -> Cost of purchased services and materials | C8: -83321046 | D8: -83321046 | E8: -1.2253191e+08 | F8: -1.2253191e+08
A9: 41200D | B9: =VLOOKUP(A9,Sheet2!A:F,1+'P&L 2018.12'!C$1,FALSE) -> Clearing account - Gross margin | C9: 0 | D9: 0 | E9: 0 | F9: 0
A10: Y1/PL/T41200 | B10: =VLOOKUP(A10,Sheet2!A:F,1+'P&L 2018.12'!C$1,FALSE) -> Changes in Inventory / COS | C10: -94270769 | D10: -94270769 | E10: -1.3862129e+08 | F10: -1.3862129e+08
A11: Y1/PL/T41000 | B11: =VLOOKUP(A11,Sheet2!A:F,1+'P&L 2018.12'!C$1,FALSE) -> Gross margin | C11: 1.549024e+08 | D11: 1.549024e+08 | E11: 2.2781272e+08 | F11: 2.2781272e+08
A12: 511000 | B12: =VLOOKUP(A12,Sheet2!A:F,1+'P&L 2018.12'!C$1,FALSE) -> Gains on the disposal of PPE | C12: 1744709.9 | D12: 1744709.9 | E12: 2565770 | F12: 2565770
A13: 511100 | B13: =VLOOKUP(A13,Sheet2!A:F,1+'P&L 2018.12'!C$1,FALSE) -> Gains on the disposal of investment property | C13: 19220955 | D13: 19220955 | E13: 28266332 | F13: 28266332
A14: 511200 | B14: =VLOOKUP(A14,Sheet2!A:F,1+'P&L 2018.12'!C$1,FALSE) -> Gains on the disposal of intangible assets | C14: 13654.06 | D14: 13654.06 | E14: 20079.65 | F14: 20079.65
A15: 511300 | B15: =VLOOKUP(A15,Sheet2!A:F,1+'P&L 2018.12'!C$1,FALSE) -> Gains on the disposal of other assets | C15: 10939.96 | D15: 10939.96 | E15: 16088.3 | F15: 16088.3
A16: 515000 | B16: =VLOOKUP(A16,Sheet2!A:F,1+'P&L 2018.12'!C$1,FALSE) -> Other income | C16: 183961.98 | D16: 183961.98 | E16: 270534.46 | F16: 270534.46
A17: Y1/PL/T51000 | B17: =VLOOKUP(A17,Sheet2!A:F,1+'P&L 2018.12'!C$1,FALSE) -> Other operating income | C17: 21174221 | D17: 21174221 | E17: 31138804 | F17: 31138804
A18: 571000 | B18: =VLOOKUP(A18,Sheet2!A:F,1+'P&L 2018.12'!C$1,FALSE) -> Amort./depr./ impair. on fixed assets | C18: -30000 | D18: -30000 | E18: -44118 | F18: -44118
A19: Y1/PL/T57000 | B19: =VLOOKUP(A19,Sheet2!A:F,1+'P&L 2018.12'!C$1,FALSE) -> Depreciation | C19: -30000 | D19: -30000 | E19: -44118 | F19: -44118
A20: 584000 | B20: =VLOOKUP(A20,Sheet2!A:F,1+'P&L 2018.12'!C$1,FALSE) -> Accruals | C20: -134732.64 | D20: -134732.64 | E20: -198137.76 | F20: -198137.76
A21: 585000 | B21: =VLOOKUP(A21,Sheet2!A:F,1+'P&L 2018.12'!C$1,FALSE) -> Other expenses | C21: -1.300568e+08 | D21: -1.300568e+08 | E21: -1.9126151e+08 | F21: -1.9126151e+08
A22: 58000D | B22: =VLOOKUP(A22,Sheet2!A:F,1+'P&L 2018.12'!C$1,FALSE) -> Clearing account - Other operating | C22: 0 | D22: 0 | E22: -0.01 | F22: -0.01
A23: Y1/PL/T58000 | B23: =VLOOKUP(A23,Sheet2!A:F,1+'P&L 2018.12'!C$1,FALSE) -> Other operating expenses | C23: -1.3019154e+08 | D23: -1.3019154e+08 | E23: -1.9145964e+08 | F23: -1.9145964e+08
A24: Y1/PL/TOI000 | B24: =VLOOKUP(A24,Sheet2!A:F,1+'P&L 2018.12'!C$1,FALSE) -> Operating income / loss | C24: 45855086 | D24: 45855086 | E24: 67447763 | F24: 67447763
A25: 601000 | B25: =VLOOKUP(A25,Sheet2!A:F,1+'P&L 2018.12'!C$1,FALSE) -> Interest income | C25: 898112.87 | D25: 898112.87 | E25: 1320764.6 | F25: 1320764.6
A26: 602000 | B26: =VLOOKUP(A26,Sheet2!A:F,1+'P&L 2018.12'!C$1,FALSE) -> Financial fair value gains or losses | C26: 19888.12 | D26: 19888.12 | E26: 29247.47 | F26: 29247.47
A27: 603000 | B27: =VLOOKUP(A27,Sheet2!A:F,1+'P&L 2018.12'!C$1,FALSE) -> Dividends | C27: 185713.42 | D27: 185713.42 | E27: 273110.59 | F27: 273110.59
A28: 604000 | B28: =VLOOKUP(A28,Sheet2!A:F,1+'P&L 2018.12'!C$1,FALSE) -> Other financial income | C28: 564307.44 | D28: 564307.44 | E28: 829870.37 | F28: 829870.37
A29: Y1/PL/T60100 | B29: =VLOOKUP(A29,Sheet2!A:F,1+'P&L 2018.12'!C$1,FALSE) -> Finance income | C29: 1668021.9 | D29: 1668021.9 | E29: 2452993 | F29: 2452993
A30: 651000 | B30: =VLOOKUP(A30,Sheet2!A:F,1+'P&L 2018.12'!C$1,FALSE) -> Allowances (reversals) for provisions on shares | C30: 0 | D30: 0 | E30: 0 | F30: 0
A31: 652000 | B31: =VLOOKUP(A31,Sheet2!A:F,1+'P&L 2018.12'!C$1,FALSE) -> Interest expenses | C31: -62705.42 | D31: -62705.42 | E31: -92214.57 | F31: -92214.57
A32: 653000 | B32: =VLOOKUP(A32,Sheet2!A:F,1+'P&L 2018.12'!C$1,FALSE) -> Other financial expenses | C32: -1557108.7 | D32: -1554507.7 | E32: -2289883.7 | F32: -2286058.7
A33: 65400D | B33: =VLOOKUP(A33,Sheet2!A:F,1+'P&L 2018.12'!C$1,FALSE) -> Clearing account - financial result | C33: 0 | D33: 0 | E33: 0.01 | F33: 0.01
A34: Y1/PL/T65100 | B34: =VLOOKUP(A34,Sheet2!A:F,1+'P&L 2018.12'!C$1,FALSE) -> Finance costs | C34: -1619814.1 | D34: -1617213.1 | E34: -2382098.3 | F34: -2378273.2
A35: Y1/PL/TFI000 | B35: =VLOOKUP(A35,Sheet2!A:F,1+'P&L 2018.12'!C$1,FALSE) -> Financial result | C35: 48207.71 | D35: 50808.73 | E35: 70894.75 | F35: 74719.81
A36: 711000 | B36: =VLOOKUP(A36,Sheet2!A:F,1+'P&L 2018.12'!C$1,FALSE) -> Share of profit - associates / JV at equity method | C36: 30070.04 | D36: 29550.04 | E36: 44221 | F36: 43456.29
A37: Y1/PL/T71000 | B37: =VLOOKUP(A37,Sheet2!A:F,1+'P&L 2018.12'!C$1,FALSE) -> Share of profit - associates / JV at equity method | C37: 30070.04 | D37: 29550.04 | E37: 44221 | F37: 43456.29
A38: Y1/PL/TBT000 | B38: =VLOOKUP(A38,Sheet2!A:F,1+'P&L 2018.12'!C$1,FALSE) -> Profit (loss) before tax | C38: 45933363 | D38: 45935444 | E38: 67562879 | F38: 67565940
A39: 721000 | B39: =VLOOKUP(A39,Sheet2!A:F,1+'P&L 2018.12'!C$1,FALSE) -> Income tax | C39: -11151789 | D39: -11151789 | E39: -16399818 | F39: -16399818
A40: 722000 | B40: =VLOOKUP(A40,Sheet2!A:F,1+'P&L 2018.12'!C$1,FALSE) -> Deferred tax | C40: 102532.87 | D40: 102532.87 | E40: 150784.85 | F40: 150784.85
A41: Y1/PL/T72000 | B41: =VLOOKUP(A41,Sheet2!A:F,1+'P&L 2018.12'!C$1,FALSE) -> Tax | C41: -11049256 | D41: -11049256 | E41: -16249033 | F41: -16249033
A42: Y1/PL/TCO100 | B42: =VLOOKUP(A42,Sheet2!A:F,1+'P&L 2018.12'!C$1,FALSE) -> Profit (loss) from continuing operations | C42: 34884107 | D42: 34886188 | E42: 51313846 | F42: 51316906
A43: 730000 | B43: =VLOOKUP(A43,Sheet2!A:F,1+'P&L 2018.12'!C$1,FALSE) -> Profit (loss) from discontinued operations | C43: -152691.49 | D43: -152691.49 | E43: -224548.1 | F43: -224548.1
A44: Y1/PL/T73000 | B44: =VLOOKUP(A44,Sheet2!A:F,1+'P&L 2018.12'!C$1,FALSE) -> Profit (loss) from discontinued operations | C44: -152691.49 | D44: -152691.49 | E44: -224548.1 | F44: -224548.1
A45: 792000 | B45: =VLOOKUP(A45,Sheet2!A:F,1+'P&L 2018.12'!C$1,FALSE) -> Net income - NCI | C45: -12640810 | D45: -12641070 | E45: -18592075 | F45: -18592457
A46: Y1/PL/TNI000 | B46: =VLOOKUP(A46,Sheet2!A:F,1+'P&L 2018.12'!C$1,FALSE) -> NET INCOME / LOSS | C46: 22090605 | D46: 22092426 | E46: 32497223 | F46: 32499901

Sheet Sheet2
B1: I_TXTMI_EN | C1: I_TXTMI_DE | D1: I_TXTMI_JA | E1: I_TXTMI_PT | F1: I_TXTMI_ZH
A2: Financial Statement Item | B2: Medium Text for FS Items | C2: Medium Text for FS Items | D2: Medium Text for FS Items | E2: Medium Text for FS Items | F2: Medium Text for FS Items
A4: 321200 | B4: NCI - Revaluation surplus before tax | C4: Minderheit - Neubewertungsrücklage vor Steuern | D4: NCI - 税引き前再評価剰余金 | E4: Interesse minorit.- exced.reaval.antes imposto | F4: NCI - 税前重估盈余
A5: 321150 | B5: NCI - Net income | C5: Minderheit - Jahresüberschuss | D5: NCI - 当期利益 | E5: Interesse minoritário - lucro líquido do exercício | F5: NCI - 净收入
A6: 321100 | B6: NCI - Reserves and retained earnings | C6: Minderheit - Rücklagen und Gewinnrücklagen | D6: NCI - 準備金および剰余金 | E6: Interesse minorit.- reservas e lucs.líqs.acums. | F6: NCI - 准备金和留存收益
A7: 317000 | B7: Net income | C7: Jahresüberschuss | D7: 当期利益 | E7: Lucro líquido do exercício | F7: 净收入
A8: 316000 | B8: Retained earnings | C8: Gewinnrücklage | D8: 剰余金 | E8: Utilização de resultado | F8: 留存收益
A9: 315100 | B9: Share of OCI & other movements - EM (local) | C9: Anteil am so. Gsmterg. u. an so. Bew. - EM (lok.) | D9: OCI およびその他移動の持分 - EM (ローカル) | E9: Participação OCI & outros movimentos - EP (local) | F9: 其他综合收入&其他移动的份额 - EM（本地）
A10: 315000 | B10: Equity component of compound financial instruments | C10: Eigenkapitalkomp. von zusammengesetzten FinInstr. | D10: 複合金融商品の資本要素 | E10: Componente patrimônio líq.instrs.fins.compostos | F10: 复合金融工具的权益组件
A11: 314900 | B11: Income tax on foreign currency translation reserve | C11: Ertragsteuer auf Währungsumrechnungsrücklage | D11: 外貨換算準備金の所得税 | E11: Imposto renda reserva conversão moeda estrangeira | F11: 外币换算准备金的所得税
A12: 314800 | B12: Foreign currency translation reserve, before tax | C12: Währungsumrechnungsrücklage, vor Steuern | D12: 税引き前外貨換算準備金 | E12: Reserva conversão moeda estrangeira, antes imposto | F12: 外币换算准备金，税前
A13: 314700 | B13: Income tax on recyclable fair value reserve | C13: Ertragsteuer auf wiederverwendb. Zeitwertrücklage | D13: 再利用時価準備金の所得税 | E13: Imposto renda sobre reserva val.atual reutilizável | F13: 可回收公允价值准备金所得税
A14: Y1/BS/T16100 | B14: Property, plant and equipment | C14: Sachanlagen | D14: 有形固定資産 | E14: Bem material | F14: 物业、工厂和设备
A15: Y1/BS/T14100 | B15: Other current financial assets | C15: Sonstige kurzfristige finanzielle Vermögenswerte | D15: その他流動金融資産 | E15: Outros imobilizados financeiros a curto prazo | F15: 其他流动金融资产
A16: Y1/BS/T13100 | B16: Inventories | C16: Vorräte | D16: 棚卸資産 | E16: Estoques | F16: 库存
A17: Y1/BS/T12300 | B17: Other current assets | C17: Sonstiges Umlaufvermögen | D17: その他流動資産 | E17: Outro ativo circulante | F17: 其他流动资产
A18: Y1/BS/T12200 | B18: Current tax assets | C18: Kurzfristige Steueransprüche | D18: 流動税金資産 | E18: Ativos de imposto a curto prazo | F18: 流动税资产
A19: Y1/BS/T12100 | B19: Trade and other current receivables | C19: Forderungen aus LuL und andere kurzfristige Ford. | D19: 売上債権およびその他流動債権 | E19: Créditos comerciais e outros a curto prazo | F19: 贸易和其他流动应收账款
A20: Y1/BS/T11100 | B20: Cash and cash equivalents | C20: Zahlungsmittel und Zahlungsmitteläquivalente | D20: 現金および現金同等物 | E20: Recursos líquidos | F20: 现金和现金等价物
A21: 604000 | B21: Other financial income | C21: Sonstige Finanzerträge | D21: その他財務収益 | E21: Outro rendimento financeiro | F21: 其他金融收入
A22: 603000 | B22: Dividends | C22: Dividenden | D22: 配当金 | E22: Dividendos | F22: 股息
A23: 602000 | B23: Financial fair value gains or losses | C23: Finanzgewinn oder -verlust Zeitwert | D23: 財務時価損益 | E23: Ganhos ou perdas valor atual financeiro | F23: 金融公允价值损益
A24: 601000 | B24: Interest income | C24: Zinserträge | D24: 受取利息 | E24: Rendimento juros | F24: 利息收入
A25: 586000 | B25: Operating fair value losses | C25: Betriebsverlust Zeitwert | D25: 営業時価損失 | E25: Perdas valor atual operacional | F25: 营业公允价值损失
A26: 585000 | B26: Other expenses | C26: Sonstiger betrieblicher Aufwand | D26: その他の費用 | E26: Outras despesas | F26: 其他费用
A27: 584000 | B27: Accruals | C27: Rückstellungen | D27: 見越 | E27: Provisões | F27: 应计
A28: 583000 | B28: Bad debt allowances | C28: Wertberichtigungen auf Forderungen | D28: 貸倒引当金 | E28: Provs.créds.irrecup. | F28: 坏账补贴
A29: 582000 | B29: Loss on the sale of shares | C29: Verlust aus dem Verkauf von Anteilen | D29: 株式売却損 | E29: Perdas na venda de participações | F29: 股份卖出损失
A30: 581000 | B30: Losses on the disposal of PPE | C30: Verluste aus dem Abgang von Sachanlagen | D30: 有形固定資産処分損 | E30: Perdas na alienação de bens materiais | F30: PPE 处置损失
A31: 572000 | B31: Impairment of goodwill | C31: Wertminderung des Geschäfts- oder Firmenwerts | D31: 連結調整勘定の減損 | E31: Depreciação de aviamento | F31: 商誉减值
A32: 571000 | B32: Amort./depr./ impair. on fixed assets | C32: Abschreibung auf Sachanlagen | D32: 固定資産の償却/減価償却/減損 | E32: Amort./deprec.imobilizados | F32: 固定资产摊销/折旧/减值
... A38: 513000 | B38: Reduction in general bad debt allowance | C38: Verminderung der Pauschalwertberichtigungen | D38: 一般貸倒引当金の減額 | E38: Redução em provisão geral créditos irrecuperáveis | F38: 常规坏账准备扣减
A39: 58000D | B39: Clearing account - Other operating | C39: Verrechnungskonto - Sonstiges Betriebsergebnis | D39: 消込勘定 - その他営業 | E39: Conta de compensação - outro resultado operacional | F39: 清账科目 - 其他运营
A40: 512000 | B40: Gains on the sale of shares | C40: Erträge aus dem Verkauf von Anteilen | D40: 株式売却益 | E40: Ganhos da venda de participações | F40: 股份卖出收益
A41: 314600 | B41: Recyclable fair value reserve, before tax | C41: Wiederverwendbare Zeitwertrücklage, vor Steuern | D41: 税引き前再利用時価準備金 | E41: Reserva val.atual reutilizável, anterior a imposto | F41: 可回收公允价值准备金，税前
A42: 262100 | B42: Warranty provision, Non-current | C42: Garantierückstellung, langfristig | D42: 非流動保証引当金 | E42: Provisão de garantia, longo prazo | F42: 非流动担保准备金
A43: 261100 | B43: Provisions for employee benefits, Non-current | C43: Rückst. für Leistungen an Arbeitnehmer, langfr. | D43: 従業員給付の非流動引当金 | E43: Provisões para benefícios empregado, longo prazo | F43: 非流动员工福利准备金
A44: 251000 | B44: Liabilities included in disposal groups HFS | C44: Verbindl. in Veräußerungsgruppen zur Veräußerung | D44: 処分グループ HFS に含まれる負債 | E44: Obrigs.incls.grupos alien.previstos p/alienação | F44: 处置组 HFS 中包括的负债
A45: 27100D | B45: Clearing account - Financial assets/liab, N-Curr | C45: VerrechKto - Fin. Vermögenswerte/Verbind., langfr. | D45: 消込勘定 - 非流動金融資産/負債 | E45: Conta compensação - imobs./passivos fins., LPrazo | F45: 清算科目 - 非流动财务资产/负债
A46: 242600 | B46: Miscellaneous provisions, Current | C46: Sonstige Rückstellungen, kurzfristig | D46: その他流動引当金 | E46: Provisões neutras, curto prazo | F46: 流动杂项准备金
A47: 242500 | B47: Prov - decommission/restor/rehab. costs, Current | C47: RüSt. - Aufw. Entsorg./Wiederherstell./Sanier., KF | D47: 引当金 - 流動廃止/復元/再生費用 | E47: Prov.- desativação/restaur./csts.reabil., crt.prz. | F47: 准备金 - 流动停用/恢复/复原成本
A48: 242400 | B48: Onerous contracts provision, Current | C48: Rückstellung für belastende Verträge, kurzfristig | D48: 流動有償契約引当金 | E48: Provisão de contratos onerosos, curto prazo | F48: 流动有偿合同准备金
A49: 242300 | B49: Legal proceedings provision, Current | C49: Prozessrückstellung, kurzfristig | D49: 流動法的手段引当金 | E49: Provisão de ações civis, curto prazo | F49: 流动法律程序准备金
A50: 242200 | B50: Restructuring provision, Current | C50: Restrukturierungsrückstellung, kurzfristig | D50: 流動再構成引当金 | E50: Provisão de reestruturação, curto prazo | F50: 流动重组准备金
A51: 242100 | B51: Warranty provision, Current | C51: Garantierückstellung, kurzfristig | D51: 流動保証引当金 | E51: Provisão de garantia, curto prazo | F51: 流动担保准备金
A52: 241100 | B52: Provisions for employee benefits, Current | C52: Rückst. für Leistungen an Arbeitnehmer, kurzfr. | D52: 従業員給付の流動引当金 | E52: Provisões para benefícios empregado, curto prazo | F52: 流动员工福利准备金
A53: 221600 | B53: Other financial liabilities, Current | C53: Sonstige finanzielle Verbindlichkeiten, kurzfr. | D53: その他流動金融負債 | E53: Outros passivos financeiros, curto prazo | F53: 其他流动金融负债
A54: 221500 | B54: Bank overdrafts, classified as cash equivalents | C54: Kontokorrentkredite, als Zahlmtteläquiv. klassif. | D54: 現金同等物に分類された銀行当座貸越 | E54: Descobs.ctas.bancs., classifs.como recursos líqs. | F54: 按现金等价物分类的银行透支
A55: 221400 | B55: Derivatives, Current | C55: Derivate, kurzfristig | D55: 流動デリバティブ | E55: Derivativos, curto prazo | F55: 流动衍生品
A56: 221300 | B56: Convertible bonds, Current | C56: Konvertible Anleihen, kurzfristig | D56: 流動転換社債 | E56: Títulos conversíveis, curto prazo | F56: 流动可兑换债券
A57: 221200 | B57: Finance leases, Current | C57: Finanzierungsleasing, kurzfristig | D57: 流動ファイナンスリース | E57: Arrendamentos financeiros, curto prazo | F57: 流动融资租赁
... A81: 281500 | B81: Debts on purchase of inv / other assets, N-Current | C81: Verbindl. aus Erwerb von Btlg./so. VermW., langfr. | D81: 棚卸資産/その他資産の購入に対する非流動債務 | E81: Dívidas compra invest./outros imobs., longo prazo | F81: 采购其他资产投资的非流动债务
A82: S00001 | B82: Group Shares (%) | C82: Kreisanteile (%) | D82: グループ持分 (%) | E82: Participações do grupo (%) | F82: 集团股份 (%)
A83: 281400 | B83: Debts on purchase / inv. in oth. entities, N-Curr | C83: Verb. aus Erwerb v. Btlg. an so. Einheiten, langfr | D83: その他エンティティの購入/投資に対する非流動債務 | E83: Dívidas compra/invest.outras ents., longo prazo | F83: 采购其他实体投资的非流动债务
A84: 281300 | B84: Debts on purchase of inv. in subs., N-Current | C84: Verbindl. aus Erwerb v. Btlg. an Tochter, langfr. | D84: 子会社への棚卸資産の購入に対する非流動債務 | E84: Dívidas compra invest.subsid., longo prazo | F84: 采购子公司投资的非流动债务
A85: 281200 | B85: Debts on purchase of intangible assets, N-Current | C85: Verbind. aus Erwerb von imm. VermögGgnst., langfr. | D85: 無形資産の購入に対する非流動債務 | E85: Dívidas na compra imobs.intangíveis, longo prazo | F85: 采购无形资产的非流动债务
A86: 281100 | B86: Debts on purchase of PPE, N-Current | C86: Verbindlichk. aus Erwerb von Sachanlagen, langfr. | D86: PPE の購入に対する非流動債務 | E86: Dívidas na compra de bens mats., longo prazo | F86: 采购物业、工厂与设备的非流动债务
A87: 271500 | B87: Other financial liabilities, Non-current | C87: Sonstige finanzielle Verbindlichkeiten, langfr. | D87: その他非流動金融負債 | E87: Outros passivos financeiros, longo prazo | F87: 其他非流动金融负债
A88: 271400 | B88: Derivatives, Non-current | C88: Derivate, langfristig | D88: 非流動デリバティブ | E88: Derivativos, longo prazo | F88: 非流动衍生品
A89: 271300 | B89: Convertible bonds, Non-current | C89: Konvertible Anleihen, langfristig | D89: 非流動転換社債 | E89: Títulos conversíveis, longo prazo | F89: 非流动可兑换债券
A90: 271200 | B90: Finance leases, Non-current | C90: Finanzierungsleasing, langfristig | D90: 非流動ファイナンスリース | E90: Arrendamentos financeiros, longo prazo | F90: 非流动融资租赁
A91: 271100 | B91: Borrowings, Non-current | C91: Fremdmittelaufnahme, langfristig | D91: 非流動借入 | E91: Empréstimos, longo prazo | F91: 非流动借款
A92: 262600 | B92: Miscellaneous provisions, Non-current | C92: Sonstige Rückstellungen, langfristig | D92: その他非流動引当金 | E92: Provisões neutras, longo prazo | F92: 非流动杂项准备金
A93: 262500 | B93: Prov - decommission/restor/rehab. costs, N-Current | C93: RüSt. - Aufw. Entsorg./Wiederherstell./Sanier., LF | D93: 引当金 - 非流動廃止/復元/再生費用 | E93: Prov.- desativação/restaur./csts.reabil., lng.prz. | F93: 准备金 - 非流动停用/恢复/复原成本
A94: 262400 | B94: Onerous contracts provision, Non-current | C94: Rückstellung für belastende Verträge, langfristig | D94: 非流動有償契約引当金 | E94: Provisão de contratos onerosos, longo prazo | F94: 非流动有偿合同准备金
A95: 28100D | B95: Clearing account - Receiv./payables, Non-current | C95: Verrechnungskonto - Ford./Verbindl., langfristig | D95: 消込勘定 - 非流動債権/債務 | E95: Cta.compensação - créditos/obrigações, longo prazo | F95: 清算科目 - 非流动应收账款/应付账款
A96: 262300 | B96: Legal proceedings provision, Non-current | C96: Prozessrückstellung, langfristig | D96: 非流動法的手段引当金 | E96: Provisão de ações civis, longo prazo | F96: 非流动法律程序准备金
A97: 262200 | B97: Restructuring provision, Non-current | C97: Restrukturierungsrückstellung, langfristig | D97: 非流動再構成引当金 | E97: Provisão de reestruturação, longo prazo | F97: 非流动重组准备金
A98: X13009 | B98: IC Other Rec Current | C98: Intern - sonstige Forderungen, kurzfristig | D98: IC その他流動債権 | E98: Outros créditos IE curto prazo
A99: X13008 | B99: IC Trade Payables | C99: Intern - Verbindlichkeiten aus LuL | D99: 会社間支払債務 | E99: Obrigações comerciais IE
A100: X13007 | B100: IC Trade Receivable | C100: Intern - Forderungen aus Lief. u. Leist. | D100: 会社間売上債権 | E100: Créditos comerciais IE
A101: X13006 | B101: Rendering services | C101: Erbringung von Dienstleistungen | D101: 実施サービス | E101: Prestação de serviços
A102: X13005 | B102: Sale of goods | C102: Verkauf von Gütern | D102: 商品販売 | E102: Venda de mercadorias
A103: X13004 | B103: PL IC Financial exp | C103: GuV - interne Finanzaufwendungen | D103: PL IC 財務費用 | E103: Resultado despesas financeiras IE
A104: X13003 | B104: PL IC Financial inc | C104: GuV - interne Finanzerträge | D104: PL IC 財務収益 | E104: Resultado rendimento financeiro IE
A105: X13002 | B105: PL IC Expense 1 | C105: GuV - interner Aufwand 1 | D105: 損益会社間費用 1 | E105: Resultado despesa IE 1
A106: X13001 | B106: PL IC OP income | C106: GuV - interne betriebliche Erträge | D106: 損益会社間営業収益 | E106: Resultado operacional IE
A107: X13000 | B107: Interunit Elimination | C107: Konzernaufrechnung | D107: 内部取引消去 | E107: Eliminações de consolidação
A108: X11004 | B108: Annual net income in BS and IS | C108: Jahresüberschuss in Bilanz und GuV | D108: BS および IS の当期純利益 | E108: Lucro líquido do exercício no balanço e DRE | F108: BS 和 IS 中的年度净收入
A109: X11003 | B109: P&L FS items translated @ average rate | C109: GuV-Positionen zum Mittelkurs umgerechnet | D109: 平均値で換算された P&L 連結勘定科目 | E109: Itens DRE convertidos @ taxa média | F109: 损益财务报表项目已按平均费率换算
A110: X11002 | B110: B/S FS items translated @ historical conversion | C110: Bilanzpositionen zum historischen Kurs umgerechnet | D110: 履歴換算で換算された B/S 連結勘定科目 | E110: Itens DRE balanço convertidos @ conversão hist. | F110: B/S 财务报表项目使用历史转换率换算
A111: X11001 | B111: B/S items translated @ closing rate | C111: Bilanzpositionen zum Schlusskurs umgerechnet | D111: 終値で換算された B/S 明細 | E111: Itens balanço convertidos @ cotação fechamento | F111: B/S 项目使用收盘汇率换算
A112: 799000 | B112: Net income/loss | C112: Jahresüberschuss/Jahresfehlbetrag | D112: 当期損益 | E112: Lucro/déficit líquido do exercício | F112: 净收入/损失
A113: 319000 | B113: Net income - clearing | C113: Jahresüberschuss - Verrechnung | D113: 当期利益 - 消込 | E113: Lucro líquido do exercício - compensação | F113: 净收入 - 清算
A114: 799999 | B114: Secondary cost element | C114: Sekundärkostenart | D114: 二次原価要素 | E114: Classe de custo secundário | F114: 次要成本要素
A115: 314100 | B115: Remeasurements of defined benefit plans, bef. tax | C115: Neubewertung von leistungsorient. Plänen, vor St. | D115: 税引き前福利プランの再測定 | E115: Reavaliações planos benefícios defs., antes imps. | F115: 重估已定义福利计划，税前
A116: 792000 | B116: Net income - NCI | C116: Jahresüberschuss - Minderheitenanteil | D116: 当期利益 - NCI | E116: Lucro líquido do exercício - interesse minoritário | F116: 净收入 - 少数股东权益
A117: 730000 | B117: Profit (loss) from discontinued operations | C117: Gewinn (Verlust) aus aufgegeb. Geschäftsbereichen | D117: 非継続事業の損益 | E117: Lucro (perda) de suspensão da atividade comercial | F117: 非持续经营的利润（损失）
A118: 722000 | B118: Deferred tax | C118: Latente Steuern | D118: 繰延税金 | E118: Impostos diferidos | F118: 递延税
A119: 721000 | B119: Income tax | C119: Ertragsteuer | D119: 所得税 | E119: Imposto de renda | F119: 所得税
A120: 711000 | B120: Share of profit - associates / JV at equity method | C120: Gewinnanteil - assoz. Unt., JV nach Equity-Methode | D120: 利益分配 - 関連会社/JV (持分法) | E120: Partic.lucros - emprs.assocs./JV em equiv.patrim. | F120: 利润份额 - 关联/JV（权益方法）
A121: 653000 | B121: Other financial expenses | C121: Sonstige Finanzaufwendungen | D121: その他財務費用 | E121: Outras despesas financeiras | F121: 其他金融费用
A122: 652000 | B122: Interest expenses | C122: Zinsaufwendungen | D122: 支払利息 | E122: Gastos com juros | F122: 利息费用
A123: 651000 | B123: Allowances (reversals) for provisions on shares | C123: Wertbericht. (Auflösung) für Rückstll. zu Anteilen | D123: 持分引当金の引当金 (取消) | E123: Fundos reserva (estornos) para provisões ações | F123: 每股准备金的补贴（冲销）
A124: 65400D | B124: Clearing account - financial result | C124: Verrechnungskonto - Finanzergebnis | D124: 消込勘定 - 財務結果 | E124: Conta de compensação - resultado financeiro | F124: 清账科目 - 财务结果
A125: X14000 | B125: Investments / Equity consolidation | C125: Beteiligungen/Equitykonsolidierung | D125: 投資/資本連結 | E125: Investimentos/equivalência patrimonial
A126: X14112 | B126: Share of OCI & other movements - EM (loc | C126: Anteil am so. Gsmterg. u. an so. Bew. - EM (lok.) | D126: OCI およびその他移動の持分 - EM (ローカル) | E126: Participação OCI & outros movimentos - EP (loc.)
A127: X14111 | B127: Equity component of compound financial i | C127: Eigenkapitalkomp. von zusammengesetzten FinInstr. | D127: 複合金融商品の資本要素 | E127: Componente patrim.líq.instrs.financeiros compostos
A128: X14110 | B128: Income tax on foreign currency translati | C128: Ertragsteuer auf Währungsumrechnungsrücklage | D128: 外貨換算の所得税 | E128: Imposto de renda sobre conversão moeda estrangeira
A129: X14109 | B129: Foreign currency translation reserve, be | C129: Währungsumrechnungsrücklage, vor Steuern | D129: 外貨換算準備金 | E129: Reserva conv.moeda estrangeira, antes impostos
...
