Workbook

Sheet Balance 2022.02
A1: Language/ Sprache/ 言語/ Linguagem >>> | B1: English | C1: =MATCH(B1, H3:L3,0) -> 1
A3: E | B3: Measures | C3: =VLOOKUP(A3,[1]Sheet2!A:F,1+'[1]Balance 2021.12 '!C$1,FALSE) -> Amount in Group Crcy | H3: English | I3: Deutsch | J3: 日本語 | K3: Portugues | L3: 中文
A4: FS Item | B4: FS Item | C4: J10 | D4: J20
A5: 111100 | B5: =VLOOKUP(A5,Sheet2!A:F,1+'Balance 2022.02'!C$1,FALSE) -> Cash on hand | C5: 26304622 | D5: 37352584
A6: 111200 | B6: =VLOOKUP(A6,Sheet2!A:F,1+'Balance 2022.02'!C$1,FALSE) -> Short-term deposits and other cash equivalents | C6: 3455192.4 | D6: 4906374.8
A7: 121100 | B7: =VLOOKUP(A7,Sheet2!A:F,1+'Balance 2022.02'!C$1,FALSE) -> Trade receivables, Gross | C7: 34193807 | D7: 48555232
A8: 121190 | B8: =VLOOKUP(A8,Sheet2!A:F,1+'Balance 2022.02'!C$1,FALSE) -> Trade receivables, Allowance | C8: -873012.25 | D8: -1239678
A9: 121200 | B9: =VLOOKUP(A9,Sheet2!A:F,1+'Balance 2022.02'!C$1,FALSE) -> Receivables on disposal of PPE, Current, Gross | C9: 7504.22 | D9: 10656
A10: 121300 | B10: =VLOOKUP(A10,Sheet2!A:F,1+'Balance 2022.02'!C$1,FALSE) -> Receivables / disp. Intang.assets, Current, Gross | C10: 4352.11 | D10: 6180
A11: 121400 | B11: =VLOOKUP(A11,Sheet2!A:F,1+'Balance 2022.02'!C$1,FALSE) -> Receivables / disp. invest. subsid, Current, Gross | C11: 990.42 | D11: 1406.4
A12: 121500 | B12: =VLOOKUP(A12,Sheet2!A:F,1+'Balance 2022.02'!C$1,FALSE) -> Receivables / disp. Inv. oth entities, Current, GV | C12: 1995.21 | D12: 2833.2
A13: 121600 | B13: =VLOOKUP(A13,Sheet2!A:F,1+'Balance 2022.02'!C$1,FALSE) -> Receivables /disp. Inv. oth assets, Current, Gross | C13: 2761.69 | D13: 3921.6
A14: 121700 | B14: =VLOOKUP(A14,Sheet2!A:F,1+'Balance 2022.02'!C$1,FALSE) -> Dividends receivable | C14: 1800 | D14: 2556
A15: 121800 | B15: =VLOOKUP(A15,Sheet2!A:F,1+'Balance 2022.02'!C$1,FALSE) -> Other receivables, Current, Gross | C15: 1084412.1 | D15: 1539866.1
A16: 121900 | B16: =VLOOKUP(A16,Sheet2!A:F,1+'Balance 2022.02'!C$1,FALSE) -> Accrued interests on receivables | C16: 49681.69 | D16: 70548
... A161: 799000 | B161: =VLOOKUP(A161,Sheet2!A:F,1+'Balance 2022.02'!C$1,FALSE) -> Net income/loss | C161: 6703108 | D161: 9344487
A162: 13100D | B162: =VLOOKUP(A162,Sheet2!A:F,1+'Balance 2022.02'!C$1,FALSE) -> Clearing Account - Gross Margin B/S | C162: 0 | D162: 0
A163: 1721HC | B163: =VLOOKUP(A163,Sheet2!A:F,1+'Balance 2022.02'!C$1,FALSE) -> Elimination of investment, held cons unit | C163: -2198133 | D163: -3157915.1
A164: 1721OC | B164: =VLOOKUP(A164,Sheet2!A:F,1+'Balance 2022.02'!C$1,FALSE) -> Elimination of investment, owner cons unit | C164: 2198133 | D164: 3157915.1
A165: 21100D | B165: =VLOOKUP(A165,Sheet2!A:F,1+'Balance 2022.02'!C$1,FALSE) -> Clearing account - Receivables/payables, Current | C165: 0 | D165: 0
A166: 21110D | B166: =VLOOKUP(A166,Sheet2!A:F,1+'Balance 2022.02'!C$1,FALSE) -> Clearing account - Trade Rec/Pay, Current | C166: -0.16 | D166: -0.24
A167: 21170D | B167: =VLOOKUP(A167,Sheet2!A:F,1+'Balance 2022.02'!C$1,FALSE) -> Clearing - Dividends rec/pay, Current | C167: 0 | D167: 0
A168: 22100D | B168: =VLOOKUP(A168,Sheet2!A:F,1+'Balance 2022.02'!C$1,FALSE) -> Clearing account - Financial assets/liab, Current | C168: -0.06 | D168: -0.08
A169: 27100D | B169: =VLOOKUP(A169,Sheet2!A:F,1+'Balance 2022.02'!C$1,FALSE) -> Clearing account - Financial assets/liab, N-Curr | C169: 0.08 | D169: 0.12
A170: 28100D | B170: =VLOOKUP(A170,Sheet2!A:F,1+'Balance 2022.02'!C$1,FALSE) -> Clearing account - Receiv./payables, Non-current | C170: -0.01 | D170: -0.02
A171: 41200D | B171: =VLOOKUP(A171,Sheet2!A:F,1+'Balance 2022.02'!C$1,FALSE) -> Clearing account - Gross margin | C171: 0 | D171: 0
A172: 58000D | B172: =VLOOKUP(A172,Sheet2!A:F,1+'Balance 2022.02'!C$1,FALSE) -> Clearing account - Other operating | C172: 0.33 | D172: 0.83
A173: 65400D | B173: =VLOOKUP(A173,Sheet2!A:F,1+'Balance 2022.02'!C$1,FALSE) -> Clearing account - financial result | C173: 0.64 | D173: -0.4

Sheet Balance sheet 2022.02
A1: Language/ Sprache/ 言語/ Linguagem >>> | B1: English | C1: =MATCH(B1, H3:L3,0) -> 1
B3: Measures | C3: Sign-Adjusted Amount in Group Crcy | H3: English | I3: Deutsch | J3: 日本語 | K3: Portugues | L3: 中文
A4: FS Item | B4: Version | C4: J10 | D4: J20
A5: 111100 | B5: =VLOOKUP(A5,Sheet2!A:F,1+'Balance sheet 2022.02'!C$1,FALSE) -> Cash on hand | C5: 26304622 | D5: 37352584
A6: 111200 | B6: =VLOOKUP(A6,Sheet2!A:F,1+'Balance sheet 2022.02'!C$1,FALSE) -> Short-term deposits and other cash equivalents | C6: 3455192.4 | D6: 4906374.8
A7: Y1/BS/T11100 | B7: =VLOOKUP(A7,Sheet2!A:F,1+'Balance sheet 2022.02'!C$1,FALSE) -> Cash and cash equivalents | C7: 29759814 | D7: 42258959
A8: 121100 | B8: =VLOOKUP(A8,Sheet2!A:F,1+'Balance sheet 2022.02'!C$1,FALSE) -> Trade receivables, Gross | C8: 34193807 | D8: 48555232
A9: 121190 | B9: =VLOOKUP(A9,Sheet2!A:F,1+'Balance sheet 2022.02'!C$1,FALSE) -> Trade receivables, Allowance | C9: -873012.25 | D9: -1239678
A10: 121200 | B10: =VLOOKUP(A10,Sheet2!A:F,1+'Balance sheet 2022.02'!C$1,FALSE) -> Receivables on disposal of PPE, Current, Gross | C10: 7504.22 | D10: 10656
A11: 121300 | B11: =VLOOKUP(A11,Sheet2!A:F,1+'Balance sheet 2022.02'!C$1,FALSE) -> Receivables / disp. Intang.assets, Current, Gross | C11: 4352.11 | D11: 6180
A12: 121400 | B12: =VLOOKUP(A12,Sheet2!A:F,1+'Balance sheet 2022.02'!C$1,FALSE) -> Receivables / disp. invest. subsid, Current, Gross | C12: 990.42 | D12: 1406.4
A13: 121500 | B13: =VLOOKUP(A13,Sheet2!A:F,1+'Balance sheet 2022.02'!C$1,FALSE) -> Receivables / disp. Inv. oth entities, Current, GV | C13: 1995.21 | D13: 2833.2
A14: 121600 | B14: =VLOOKUP(A14,Sheet2!A:F,1+'Balance sheet 2022.02'!C$1,FALSE) -> Receivables /disp. Inv. oth assets, Current, Gross | C14: 2761.69 | D14: 3921.6
A15: 121700 | B15: =VLOOKUP(A15,Sheet2!A:F,1+'Balance sheet 2022.02'!C$1,FALSE) -> Dividends receivable | C15: 1800 | D15: 2556
A16: 121800 | B16: =VLOOKUP(A16,Sheet2!A:F,1+'Balance sheet 2022.02'!C$1,FALSE) -> Other receivables, Current, Gross | C16: 1084412.1 | D16: 1539866.1
A17: 121900 | B17: =VLOOKUP(A17,Sheet2!A:F,1+'Balance sheet 2022.02'!C$1,FALSE) -> Accrued interests on receivables | C17: 49681.69 | D17: 70548
A18: 121990 | B18: =VLOOKUP(A18,Sheet2!A:F,1+'Balance sheet 2022.02'!C$1,FALSE) -> Other receivables, Allow | C18: -19963.38 | D18: -28348
A19: Y1/BS/T12100 | B19: =VLOOKUP(A19,Sheet2!A:F,1+'Balance sheet 2022.02'!C$1,FALSE) -> Trade and other current receivables | C19: 34454328 | D19: 48925173
A20: 122100 | B20: =VLOOKUP(A20,Sheet2!A:F,1+'Balance sheet 2022.02'!C$1,FALSE) -> Income tax receivables | C20: 0 | D20: 0
A21: Y1/BS/T12200 | B21: =VLOOKUP(A21,Sheet2!A:F,1+'Balance sheet 2022.02'!C$1,FALSE) -> Current tax assets | C21: 0 | D21: 0
A22: 123100 | B22: =VLOOKUP(A22,Sheet2!A:F,1+'Balance sheet 2022.02'!C$1,FALSE) -> Prepaid expenses | C22: 63429.05 | D22: 90069.31
A23: Y1/BS/T12300 | B23: =VLOOKUP(A23,Sheet2!A:F,1+'Balance sheet 2022.02'!C$1,FALSE) -> Other current assets | C23: 63429.05 | D23: 90069.31
A24: 131100 | B24: =VLOOKUP(A24,Sheet2!A:F,1+'Balance sheet 2022.02'!C$1,FALSE) -> Raw materials | C24: 2989078.3 | D24: 4244493.8
A25: 131200 | B25: =VLOOKUP(A25,Sheet2!A:F,1+'Balance sheet 2022.02'!C$1,FALSE) -> Merchandise | C25: 3644655.3 | D25: 5175413.8
A26: 131300 | B26: =VLOOKUP(A26,Sheet2!A:F,1+'Balance sheet 2022.02'!C$1,FALSE) -> Production supplies | C26: 2912.11 | D26: 4135.2
A27: 131400 | B27: =VLOOKUP(A27,Sheet2!A:F,1+'Balance sheet 2022.02'!C$1,FALSE) -> Work in progress | C27: 901848.7 | D27: 1280625.9
A28: 131500 | B28: =VLOOKUP(A28,Sheet2!A:F,1+'Balance sheet 2022.02'!C$1,FALSE) -> Finished goods | C28: 920917.06 | D28: 1307703.1
A29: 131600 | B29: =VLOOKUP(A29,Sheet2!A:F,1+'Balance sheet 2022.02'!C$1,FALSE) -> Other inventories | C29: 1966.48 | D29: 2792.4
A30: 13100D | B30: =VLOOKUP(A30,Sheet2!A:F,1+'Balance sheet 2022.02'!C$1,FALSE) -> Clearing Account - Gross Margin B/S | C30: 0 | D30: 0
A31: Y1/BS/T13100 | B31: =VLOOKUP(A31,Sheet2!A:F,1+'Balance sheet 2022.02'!C$1,FALSE) -> Inventories | C31: 8461377.9 | D31: 12015164
A32: 141100 | B32: =VLOOKUP(A32,Sheet2!A:F,1+'Balance sheet 2022.02'!C$1,FALSE) -> Other financial assets at FVTOCI, Current | C32: 18100 | D32: 25702
A33: 141200 | B33: =VLOOKUP(A33,Sheet2!A:F,1+'Balance sheet 2022.02'!C$1,FALSE) -> Derivatives, Current | C33: 4908 | D33: 6969.36
A34: 141300 | B34: =VLOOKUP(A34,Sheet2!A:F,1+'Balance sheet 2022.02'!C$1,FALSE) -> Financial assets at FVPL, Current | C34: 5840 | D34: 8292.8
A35: 141400 | B35: =VLOOKUP(A35,Sheet2!A:F,1+'Balance sheet 2022.02'!C$1,FALSE) -> Loans and cash advances, Current, Gross | C35: 39576.82 | D35: 56199.08
A36: 141490 | B36: =VLOOKUP(A36,Sheet2!A:F,1+'Balance sheet 2022.02'!C$1,FALSE) -> Loans and cash advances, Current, Allowance | C36: -9456.34 | D36: -13428
A37: Y1/BS/T14100 | B37: =VLOOKUP(A37,Sheet2!A:F,1+'Balance sheet 2022.02'!C$1,FALSE) -> Other current financial assets | C37: 58968.48 | D37: 83735.24
A38: Y1/BS/TAC100 | B38: =VLOOKUP(A38,Sheet2!A:F,1+'Balance sheet 2022.02'!C$1,FALSE) -> Current assets oth.than incl.in disposal groups | C38: 72797918 | D38: 1.033731e+08
A39: 151100 | B39: =VLOOKUP(A39,Sheet2!A:F,1+'Balance sheet 2022.02'!C$1,FALSE) -> NC assets or disp. groups classified HFS | C39: 2000 | D39: 2840
A40: Y1/BS/TAC200 | B40: =VLOOKUP(A40,Sheet2!A:F,1+'Balance sheet 2022.02'!C$1,FALSE) -> NC assets or disp. groups classified HFS/HDO | C40: 2000 | D40: 2840
A41: Y1/BS/TAC000 | B41: =VLOOKUP(A41,Sheet2!A:F,1+'Balance sheet 2022.02'!C$1,FALSE) -> Current assets | C41: 72799918 | D41: 1.0337594e+08
A42: 161100 | B42: =VLOOKUP(A42,Sheet2!A:F,1+'Balance sheet 2022.02'!C$1,FALSE) -> Lands and buildings | C42: 21178853 | D42: 30073987
A43: 161190 | B43: =VLOOKUP(A43,Sheet2!A:F,1+'Balance sheet 2022.02'!C$1,FALSE) -> Lands and buildings, Depreciation | C43: -6727684.9 | D43: -9553370.6
A44: 161200 | B44: =VLOOKUP(A44,Sheet2!A:F,1+'Balance sheet 2022.02'!C$1,FALSE) -> Tangibles assets under construction | C44: 1106367.8 | D44: 1571043.1
A45: 161300 | B45: =VLOOKUP(A45,Sheet2!A:F,1+'Balance sheet 2022.02'!C$1,FALSE) -> Office equipment | C45: 272058.67 | D45: 386323.41
A46: 161390 | B46: =VLOOKUP(A46,Sheet2!A:F,1+'Balance sheet 2022.02'!C$1,FALSE) -> Office equipment, Depreciation | C46: -77279.33 | D46: -109736.69
A47: 161400 | B47: =VLOOKUP(A47,Sheet2!A:F,1+'Balance sheet 2022.02'!C$1,FALSE) -> Vehicles | C47: 80904.22 | D47: 114884
A48: 161490 | B48: =VLOOKUP(A48,Sheet2!A:F,1+'Balance sheet 2022.02'!C$1,FALSE) -> Vehicles, Depreciation | C48: -53585.92 | D48: -76092
A49: 161500 | B49: =VLOOKUP(A49,Sheet2!A:F,1+'Balance sheet 2022.02'!C$1,FALSE) -> Machinery | C49: 47386.76 | D49: 67289.2
A50: 161590 | B50: =VLOOKUP(A50,Sheet2!A:F,1+'Balance sheet 2022.02'!C$1,FALSE) -> Machinery, Depreciation | C50: -20677.72 | D50: -29362.36
A51: 161600 | B51: =VLOOKUP(A51,Sheet2!A:F,1+'Balance sheet 2022.02'!C$1,FALSE) -> Other property, plant and equipment | C51: 796069.86 | D51: 1130419.2
A52: 161690 | B52: =VLOOKUP(A52,Sheet2!A:F,1+'Balance sheet 2022.02'!C$1,FALSE) -> Other property, plant and equipment, Depreciation | C52: -389023.24 | D52: -552413
A53: Y1/BS/T16100 | B53: =VLOOKUP(A53,Sheet2!A:F,1+'Balance sheet 2022.02'!C$1,FALSE) -> Property, plant and equipment | C53: 16213389 | D53: 23022971
A54: 162100 | B54: =VLOOKUP(A54,Sheet2!A:F,1+'Balance sheet 2022.02'!C$1,FALSE) -> Investment property | C54: 106646.48 | D54: 151438
A55: 162190 | B55: =VLOOKUP(A55,Sheet2!A:F,1+'Balance sheet 2022.02'!C$1,FALSE) -> Investment property, Depreciation | C55: -17310.35 | D55: -24580.7
A56: Y1/BS/T16200 | B56: =VLOOKUP(A56,Sheet2!A:F,1+'Balance sheet 2022.02'!C$1,FALSE) -> Investment property | C56: 89336.13 | D56: 126857.3
A57: 163100 | B57: =VLOOKUP(A57,Sheet2!A:F,1+'Balance sheet 2022.02'!C$1,FALSE) -> Goodwill | C57: 950833.1 | D57: 1350183
A58: Y1/BS/T16300 | B58: =VLOOKUP(A58,Sheet2!A:F,1+'Balance sheet 2022.02'!C$1,FALSE) -> Goodwill | C58: 950833.1 | D58: 1350183
A59: 164100 | B59: =VLOOKUP(A59,Sheet2!A:F,1+'Balance sheet 2022.02'!C$1,FALSE) -> Brand names | C59: 470431.91 | D59: 668013.64
A60: 164190 | B60: =VLOOKUP(A60,Sheet2!A:F,1+'Balance sheet 2022.02'!C$1,FALSE) -> Brand names, Amortization | C60: -12831.81 | D60: -18221.18
A61: 164200 | B61: =VLOOKUP(A61,Sheet2!A:F,1+'Balance sheet 2022.02'!C$1,FALSE) -> Computer software | C61: 6347918.5 | D61: 9014049
A62: 164290 | B62: =VLOOKUP(A62,Sheet2!A:F,1+'Balance sheet 2022.02'!C$1,FALSE) -> Computer software, Amortization | C62: -3015792.1 | D62: -4282427
A63: 164300 | B63: =VLOOKUP(A63,Sheet2!A:F,1+'Balance sheet 2022.02'!C$1,FALSE) -> Patents, trademarks and other rights | C63: 873135.22 | D63: 1239852
A64: 164390 | B64: =VLOOKUP(A64,Sheet2!A:F,1+'Balance sheet 2022.02'!C$1,FALSE) -> Patents, trademarks and other rights, Amortization | C64: -593122.53 | D64: -842234
A65: 164400 | B65: =VLOOKUP(A65,Sheet2!A:F,1+'Balance sheet 2022.02'!C$1,FALSE) -> Intangible assets under development | C65: 66351.98 | D65: 94219.8
A66: 164490 | B66: =VLOOKUP(A66,Sheet2!A:F,1+'Balance sheet 2022.02'!C$1,FALSE) -> Intangible assets under development, Impairment | C66: -21814.08 | D66: -30976
A67: 164500 | B67: =VLOOKUP(A67,Sheet2!A:F,1+'Balance sheet 2022.02'!C$1,FALSE) -> Other intangible assets | C67: 21907.18 | D67: 31108.2
A68: 164590 | B68: =VLOOKUP(A68,Sheet2!A:F,1+'Balance sheet 2022.02'!C$1,FALSE) -> Other intangible assets, Amortization | C68: -11400.14 | D68: -16188.2
A69: Y1/BS/T16400 | B69: =VLOOKUP(A69,Sheet2!A:F,1+'Balance sheet 2022.02'!C$1,FALSE) -> Intangible assets | C69: 4124784.2 | D69: 5857196.3
A70: 171000 | B70: =VLOOKUP(A70,Sheet2!A:F,1+'Balance sheet 2022.02'!C$1,FALSE) -> Investments accounted for using equity method | C70: 87088.04 | D70: 123665.02
A71: Y1/BS/T17100 | B71: =VLOOKUP(A71,Sheet2!A:F,1+'Balance sheet 2022.02'!C$1,FALSE) -> Investments accounted for using equity method | C71: 87088.04 | D71: 123665.02
A72: 172100 | B72: =VLOOKUP(A72,Sheet2!A:F,1+'Balance sheet 2022.02'!C$1,FALSE) -> Investments in subs, JV and associates, GV | C72: 0 | D72: 0
A73: 1721OC | B73: =VLOOKUP(A73,Sheet2!A:F,1+'Balance sheet 2022.02'!C$1,FALSE) -> Elimination of investment, owner cons unit | C73: 2198133 | D73: 3157915.1
A74: 1721HC | B74: =VLOOKUP(A74,Sheet2!A:F,1+'Balance sheet 2022.02'!C$1,FALSE) -> Elimination of investment, held cons unit | C74: -2198133 | D74: -3157915.1
A75: 172190 | B75: =VLOOKUP(A75,Sheet2!A:F,1+'Balance sheet 2022.02'!C$1,FALSE) -> Investments in subs, JV and associates, Impair | C75: 0 | D75: -0.2
A76: 172200 | B76: =VLOOKUP(A76,Sheet2!A:F,1+'Balance sheet 2022.02'!C$1,FALSE) -> Other financial assets at FVTOCI, Non-current | C76: 6599.44 | D76: 9371.2
A77: 172400 | B77: =VLOOKUP(A77,Sheet2!A:F,1+'Balance sheet 2022.02'!C$1,FALSE) -> Financial assets at FVPL, Non-current | C77: 1800 | D77: 2556
A78: Y1/BS/T17200 | B78: =VLOOKUP(A78,Sheet2!A:F,1+'Balance sheet 2022.02'!C$1,FALSE) -> Other non-current financial assets | C78: 8399.44 | D78: 11927
A79: 181100 | B79: =VLOOKUP(A79,Sheet2!A:F,1+'Balance sheet 2022.02'!C$1,FALSE) -> Loans and cash advances, Non-current, Gross | C79: 254041.12 | D79: 360738.51
A80: 181190 | B80: =VLOOKUP(A80,Sheet2!A:F,1+'Balance sheet 2022.02'!C$1,FALSE) -> Loans and cash advances, Non-current, Allowance | C80: -9981.69 | D80: -14174
A81: 181200 | B81: =VLOOKUP(A81,Sheet2!A:F,1+'Balance sheet 2022.02'!C$1,FALSE) -> Receivables on disposal of PPE, N-Current, Gross | C81: 5104.22 | D81: 7248
A82: 181300 | B82: =VLOOKUP(A82,Sheet2!A:F,1+'Balance sheet 2022.02'!C$1,FALSE) -> Receiv./ disp. Intang.assets, N-Current, Gross | C82: 1590.43 | D82: 2258.42
A83: 181400 | B83: =VLOOKUP(A83,Sheet2!A:F,1+'Balance sheet 2022.02'!C$1,FALSE) -> Receiv./ disp. invest. subsid, N-Current, Gross | C83: 21312.68 | D83: 30264
A84: 181500 | B84: =VLOOKUP(A84,Sheet2!A:F,1+'Balance sheet 2022.02'!C$1,FALSE) -> Receiv. / disp. Inv. oth entities, N-Current, GV | C84: 4352.11 | D84: 6180
A85: 181600 | B85: =VLOOKUP(A85,Sheet2!A:F,1+'Balance sheet 2022.02'!C$1,FALSE) -> Receiv. /disp. Inv. oth assets, N-Current, Gross | C85: 5104.22 | D85: 7248
A86: 181800 | B86: =VLOOKUP(A86,Sheet2!A:F,1+'Balance sheet 2022.02'!C$1,FALSE) -> Other receivables, Non-current, Gross | C86: 198118.31 | D86: 281328
A87: 181890 | B87: =VLOOKUP(A87,Sheet2!A:F,1+'Balance sheet 2022.02'!C$1,FALSE) -> Receivables, Non-current, Allowance | C87: -16811.27 | D87: -23872
A88: Y1/BS/T18100 | B88: =VLOOKUP(A88,Sheet2!A:F,1+'Balance sheet 2022.02'!C$1,FALSE) -> Non-current receivables | C88: 462830.13 | D88: 657218.93
A89: 182100 | B89: =VLOOKUP(A89,Sheet2!A:F,1+'Balance sheet 2022.02'!C$1,FALSE) -> Deferred tax assets | C89: 700 | D89: 975.45
A90: Y1/BS/T18200 | B90: =VLOOKUP(A90,Sheet2!A:F,1+'Balance sheet 2022.02'!C$1,FALSE) -> Deferred tax assets | C90: 700 | D90: 975.45
A91: Y1/BS/TANC00 | B91: =VLOOKUP(A91,Sheet2!A:F,1+'Balance sheet 2022.02'!C$1,FALSE) -> Non Current assets | C91: 21937360 | D91: 31150994
A92: Y1/BS/TA0000 | B92: =VLOOKUP(A92,Sheet2!A:F,1+'Balance sheet 2022.02'!C$1,FALSE) -> Assets | C92: 94737278 | D92: 1.3452693e+08
A93: 211100 | B93: =VLOOKUP(A93,Sheet2!A:F,1+'Balance sheet 2022.02'!C$1,FALSE) -> Trade payables | C93: 27537864 | D93: 39103790
A94: 21110D | B94: =VLOOKUP(A94,Sheet2!A:F,1+'Balance sheet 2022.02'!C$1,FALSE) -> Clearing account - Trade Rec/Pay, Current | C94: 0.16 | D94: 0.24
A95: 211200 | B95: =VLOOKUP(A95,Sheet2!A:F,1+'Balance sheet 2022.02'!C$1,FALSE) -> Debts on purchase of PPE, Current | C95: 2011.26 | D95: 2856
A96: 211300 | B96: =VLOOKUP(A96,Sheet2!A:F,1+'Balance sheet 2022.02'!C$1,FALSE) -> Debts on purchase of intangible assets, Current | C96: 4923.38 | D96: 6991.2
A97: 211400 | B97: =VLOOKUP(A97,Sheet2!A:F,1+'Balance sheet 2022.02'!C$1,FALSE) -> Debts on purchase of inv. in subs., Current | C97: 2822.54 | D97: 4008
A98: 211500 | B98: =VLOOKUP(A98,Sheet2!A:F,1+'Balance sheet 2022.02'!C$1,FALSE) -> Debts on purchase / inv. in oth. entities, Current | C98: 2552.11 | D98: 3624
A99: 211600 | B99: =VLOOKUP(A99,Sheet2!A:F,1+'Balance sheet 2022.02'!C$1,FALSE) -> Debts on purchase of inv / other assets, Current | C99: 1771.27 | D99: 2515.2
A100: 211700 | B100: =VLOOKUP(A100,Sheet2!A:F,1+'Balance sheet 2022.02'!C$1,FALSE) -> Dividends payable | C100: 3542.53 | D100: 5030.4
A101: 21170D | B101: =VLOOKUP(A101,Sheet2!A:F,1+'Balance sheet 2022.02'!C$1,FALSE) -> Clearing - Dividends rec/pay, Current | C101: 0 | D101: 0
...

Sheet P&L 2022.02
A1: Language/ Sprache/ 言語/ Linguagem >>> | B1: English | C1: =MATCH(B1, H3:L3,0) -> 1
B3: Measures | C3: Sign-Adjusted Amount in Group Crcy | H3: English | I3: Deutsch | J3: 日本語 | K3: Portugues | L3: 中文
A4: FS Item | B4: FS Item | C4: J10 | D4: J20
A5: 411100 | B5: =VLOOKUP(A5,Sheet2!A:F,1+'P&L 2022.02'!C$1,FALSE) -> Sale of goods | C5: 3.6538595e+08 | D5: 5.1077408e+08
A6: Y1/PL/T41100 | B6: =VLOOKUP(A6,Sheet2!A:F,1+'P&L 2022.02'!C$1,FALSE) -> Revenue | C6: 3.6538595e+08 | D6: 5.1077408e+08
A7: 412100 | B7: =VLOOKUP(A7,Sheet2!A:F,1+'P&L 2022.02'!C$1,FALSE) -> Changes in Inventory | C7: -18046815 | D7: -25194846
A8: 412200 | B8: =VLOOKUP(A8,Sheet2!A:F,1+'P&L 2022.02'!C$1,FALSE) -> Cost of purchased services and materials | C8: -1.1437499e+08 | D8: -1.5992096e+08
A9: 41200D | B9: =VLOOKUP(A9,Sheet2!A:F,1+'P&L 2022.02'!C$1,FALSE) -> Clearing account - Gross margin | C9: 0 | D9: 0
A10: Y1/PL/T41200 | B10: =VLOOKUP(A10,Sheet2!A:F,1+'P&L 2022.02'!C$1,FALSE) -> Changes in Inventory / COS | C10: -1.324218e+08 | D10: -1.8511581e+08
A11: Y1/PL/T41000 | B11: =VLOOKUP(A11,Sheet2!A:F,1+'P&L 2022.02'!C$1,FALSE) -> Gross margin | C11: 2.3296415e+08 | D11: 3.2565827e+08
A12: 511000 | B12: =VLOOKUP(A12,Sheet2!A:F,1+'P&L 2022.02'!C$1,FALSE) -> Gains on the disposal of PPE | C12: 292362.21 | D12: 408133.48
A13: 511200 | B13: =VLOOKUP(A13,Sheet2!A:F,1+'P&L 2022.02'!C$1,FALSE) -> Gains on the disposal of intangible assets | C13: 653.49 | D13: 912.27
A14: 511300 | B14: =VLOOKUP(A14,Sheet2!A:F,1+'P&L 2022.02'!C$1,FALSE) -> Gains on the disposal of other assets | C14: 465.54 | D14: 648.97
A15: 512000 | B15: =VLOOKUP(A15,Sheet2!A:F,1+'P&L 2022.02'!C$1,FALSE) -> Gains on the sale of shares | C15: 347424 | D15: 468278.6
A16: 515000 | B16: =VLOOKUP(A16,Sheet2!A:F,1+'P&L 2022.02'!C$1,FALSE) -> Other income | C16: 42254.66 | D16: 58988.15
A17: Y1/PL/T51000 | B17: =VLOOKUP(A17,Sheet2!A:F,1+'P&L 2022.02'!C$1,FALSE) -> Other operating income | C17: 683159.9 | D17: 936961.47
A18: 585000 | B18: =VLOOKUP(A18,Sheet2!A:F,1+'P&L 2022.02'!C$1,FALSE) -> Other expenses | C18: -2.148743e+08 | D18: -3.0038157e+08
A19: 58000D | B19: =VLOOKUP(A19,Sheet2!A:F,1+'P&L 2022.02'!C$1,FALSE) -> Clearing account - Other operating | C19: -0.33 | D19: -0.83
A20: Y1/PL/T58000 | B20: =VLOOKUP(A20,Sheet2!A:F,1+'P&L 2022.02'!C$1,FALSE) -> Other operating expenses | C20: -2.148743e+08 | D20: -3.0038157e+08
A21: Y1/PL/TOI000 | B21: =VLOOKUP(A21,Sheet2!A:F,1+'P&L 2022.02'!C$1,FALSE) -> Operating income / loss | C21: 18773011 | D21: 26213656
A22: 601000 | B22: =VLOOKUP(A22,Sheet2!A:F,1+'P&L 2022.02'!C$1,FALSE) -> Interest income | C22: 281426.13 | D22: 392878.7
A23: 602000 | B23: =VLOOKUP(A23,Sheet2!A:F,1+'P&L 2022.02'!C$1,FALSE) -> Financial fair value gains or losses | C23: 5636.45 | D23: 7868.63
A24: 603000 | B24: =VLOOKUP(A24,Sheet2!A:F,1+'P&L 2022.02'!C$1,FALSE) -> Dividends | C24: 578749 | D24: 806370.98
A25: 604000 | B25: =VLOOKUP(A25,Sheet2!A:F,1+'P&L 2022.02'!C$1,FALSE) -> Other financial income | C25: 146403.13 | D25: 204380.19
A26: Y1/PL/T60100 | B26: =VLOOKUP(A26,Sheet2!A:F,1+'P&L 2022.02'!C$1,FALSE) -> Finance income | C26: 1012214.7 | D26: 1411498.5
A27: 652000 | B27: =VLOOKUP(A27,Sheet2!A:F,1+'P&L 2022.02'!C$1,FALSE) -> Interest expenses | C27: -26702 | D27: -37277.58
A28: 653000 | B28: =VLOOKUP(A28,Sheet2!A:F,1+'P&L 2022.02'!C$1,FALSE) -> Other financial expenses | C28: -1809727.3 | D28: -2529646
A29: 65400D | B29: =VLOOKUP(A29,Sheet2!A:F,1+'P&L 2022.02'!C$1,FALSE) -> Clearing account - financial result | C29: -0.64 | D29: 0.4
A30: Y1/PL/T65100 | B30: =VLOOKUP(A30,Sheet2!A:F,1+'P&L 2022.02'!C$1,FALSE) -> Finance costs | C30: -1836429.9 | D30: -2566923.1
A31: Y1/PL/TFI000 | B31: =VLOOKUP(A31,Sheet2!A:F,1+'P&L 2022.02'!C$1,FALSE) -> Financial result | C31: -824215.24 | D31: -1155424.6
A32: 711000 | B32: =VLOOKUP(A32,Sheet2!A:F,1+'P&L 2022.02'!C$1,FALSE) -> Share of profit - associates / JV at equity method | C32: 10400 | D32: 14512.03
A33: Y1/PL/T71000 | B33: =VLOOKUP(A33,Sheet2!A:F,1+'P&L 2022.02'!C$1,FALSE) -> Share of profit - associates / JV at equity method | C33: 10400 | D33: 14512.03
A34: Y1/PL/TBT000 | B34: =VLOOKUP(A34,Sheet2!A:F,1+'P&L 2022.02'!C$1,FALSE) -> Profit (loss) before tax | C34: 17959196 | D34: 25072744
A35: 721000 | B35: =VLOOKUP(A35,Sheet2!A:F,1+'P&L 2022.02'!C$1,FALSE) -> Income tax | C35: -9894489.5 | D35: -13826887
A36: 722000 | B36: =VLOOKUP(A36,Sheet2!A:F,1+'P&L 2022.02'!C$1,FALSE) -> Deferred tax | C36: 126105.31 | D36: 176052.59
A37: Y1/PL/T72000 | B37: =VLOOKUP(A37,Sheet2!A:F,1+'P&L 2022.02'!C$1,FALSE) -> Tax | C37: -9768384.2 | D37: -13650835
A38: Y1/PL/TCO100 | B38: =VLOOKUP(A38,Sheet2!A:F,1+'P&L 2022.02'!C$1,FALSE) -> Profit (loss) from continuing operations | C38: 8190811.4 | D38: 11421909
A39: 730000 | B39: =VLOOKUP(A39,Sheet2!A:F,1+'P&L 2022.02'!C$1,FALSE) -> Profit (loss) from discontinued operations | C39: -180992.28 | D39: -252678.13
A40: Y1/PL/T73000 | B40: =VLOOKUP(A40,Sheet2!A:F,1+'P&L 2022.02'!C$1,FALSE) -> Profit (loss) from discontinued operations | C40: -180992.28 | D40: -252678.13
A41: 792000 | B41: =VLOOKUP(A41,Sheet2!A:F,1+'P&L 2022.02'!C$1,FALSE) -> Net income - NCI | C41: -1306711.1 | D41: -1824743.9
A42: Y1/PL/TNI000 | B42: =VLOOKUP(A42,Sheet2!A:F,1+'P&L 2022.02'!C$1,FALSE) -> NET INCOME / LOSS | C42: 6703108 | D42: 9344487

Sheet Sheet2
B1: I_TXTMI_EN | C1: I_TXTMI_DE | D1: I_TXTMI_JA | E1: I_TXTMI_PT | F1: I_TXTMI_ZH
A2: Financial Statement Item | B2: Medium Text for FS Items | C2: Medium Text for FS Items | D2: Medium Text for FS Items | E2: Medium Text for FS Items | F2: Medium Text for FS Items
A4: 321200 | B4: NCI - Revaluation surplus before tax | C4: Minderheit - Neubewertungsrücklage vor Steuern | D4: NCI - 税引き前再評価剰余金 | E4: Interesse minorit.- exced.reaval.antes imposto | F4: NCI - 税前重估盈余
A5: 321150 | B5: NCI - Net income | C5: Minderheit - Jahresüberschuss | D5: NCI - 当期利益 | E5: Interesse minoritário - lucro líquido do exercício | F5: NCI - 净收入
A6: 321100 | B6: NCI - Reserves and retained earnings | C6: Minderheit - Rücklagen und Gewinnrücklagen | D6: NCI - 準備金および剰余金 | E6: Interesse minorit.- reservas e lucs.líqs.acums. | F6: NCI - 准备金和留存收益
A7: 317000 | B7: Net income | C7: Jahresüberschuss | D7: 当期利益 | E7: Lucro líquido do exercício | F7: 净收入
A8: 316000 | B8: Retained earnings | C8: Gewinnrücklage | D8: 剰余金 | E8: Utilização de resultado | F8: 留存收益
A9: 315100 | B9: Share of OCI & other movements - EM (local) | C9: Anteil am so. Gsmterg. u. an so. Bew. - EM (lok.) | D9: OCI およびその他移動の持分 - EM (ローカル) | E9: Participação OCI & outros movimentos - EP (local) | F9: 其他综合收入&其他移动的份额 - EM（本地）
A10: 315000 | B10: Equity component of compound financial instruments | C10: Eigenkapitalkomp. von zusammengesetzten FinInstr. | D10: 複合金融商品の資本要素 | E10: Componente patrimônio líq.instrs.fins.compostos | F10: 复合金融工具的权益组件
A11: 314900 | B11: Income tax on foreign currency translation reserve | C11: Ertragsteuer auf Währungsumrechnungsrücklage | D11: 外貨換算準備金の所得税 | E11: Imposto renda reserva conversão moeda estrangeira | F11: 外币换算准备金的所得税
A12: 314800 | B12: Foreign currency translation reserve, before tax | C12: Währungsumrechnungsrücklage, vor Steuern | D12: 税引き前外貨換算準備金 | E12: Reserva conversão moeda estrangeira, antes imposto | F12: 外币换算准备金，税前
A13: 314700 | B13: Income tax on recyclable fair value reserve | C13: Ertragsteuer auf wiederverwendb. Zeitwertrücklage | D13: 再利用時価準備金の所得税 | E13: Imposto renda sobre reserva val.atual reutilizável | F13: 可回收公允价值准备金所得税
A14: Y1/BS/T16100 | B14: Property, plant and equipment | C14: Sachanlagen | D14: 有形固定資産 | E14: Bem material | F14: 物业、工厂和设备
A15: Y1/BS/T14100 | B15: Other current financial assets | C15: Sonstige kurzfristige finanzielle Vermögenswerte | D15: その他流動金融資産 | E15: Outros imobilizados financeiros a curto prazo | F15: 其他流动金融资产
A16: Y1/BS/T13100 | B16: Inventories | C16: Vorräte | D16: 棚卸資産 | E16: Estoques | F16: 库存
A17: Y1/BS/T12300 | B17: Other current assets | C17: Sonstiges Umlaufvermögen | D17: その他流動資産 | E17: Outro ativo circulante | F17: 其他流动资产
A18: Y1/BS/T12200 | B18: Current tax assets | C18: Kurzfristige Steueransprüche | D18: 流動税金資産 | E18: Ativos de imposto a curto prazo | F18: 流动税资产
A19: Y1/BS/T12100 | B19: Trade and other current receivables | C19: Forderungen aus LuL und andere kurzfristige Ford. | D19: 売上債権およびその他流動債権 | E19: Créditos comerciais e outros a curto prazo | F19: 贸易和其他流动应收账款
A20: Y1/BS/T11100 | B20: Cash and cash equivalents | C20: Zahlungsmittel und Zahlungsmitteläquivalente | D20: 現金および現金同等物 | E20: Recursos líquidos | F20: 现金和现金等价物
A21: 604000 | B21: Other financial income | C21: Sonstige Finanzerträge | D21: その他財務収益 | E21: Outro rendimento financeiro | F21: 其他金融收入
A22: 603000 | B22: Dividends | C22: Dividenden | D22: 配当金 | E22: Dividendos | F22: 股息
A23: 602000 | B23: Financial fair value gains or losses | C23: Finanzgewinn oder -verlust Zeitwert | D23: 財務時価損益 | E23: Ganhos ou perdas valor atual financeiro | F23: 金融公允价值损益
A24: 601000 | B24: Interest income | C24: Zinserträge | D24: 受取利息 | E24: Rendimento juros | F24: 利息收入
A25: 586000 | B25: Operating fair value losses | C25: Betriebsverlust Zeitwert | D25: 営業時価損失 | E25: Perdas valor atual operacional | F25: 营业公允价值损失
A26: 585000 | B26: Other expenses | C26: Sonstiger betrieblicher Aufwand | D26: その他の費用 | E26: Outras despesas | F26: 其他费用
A27: 584000 | B27: Accruals | C27: Rückstellungen | D27: 見越 | E27: Provisões | F27: 应计
A28: 583000 | B28: Bad debt allowances | C28: Wertberichtigungen auf Forderungen | D28: 貸倒引当金 | E28: Provs.créds.irrecup. | F28: 坏账补贴
A29: 582000 | B29: Loss on the sale of shares | C29: Verlust aus dem Verkauf von Anteilen | D29: 株式売却損 | E29: Perdas na venda de participações | F29: 股份卖出损失
A30: 581000 | B30: Losses on the disposal of PPE | C30: Verluste aus dem Abgang von Sachanlagen | D30: 有形固定資産処分損 | E30: Perdas na alienação de bens materiais | F30: PPE 处置损失
A31: 572000 | B31: Impairment of goodwill | C31: Wertminderung des Geschäfts- oder Firmenwerts | D31: 連結調整勘定の減損 | E31: Depreciação de aviamento | F31: 商誉减值
A32: 571000 | B32: Amort./depr./ impair. on fixed assets | C32: Abschreibung auf Sachanlagen | D32: 固定資産の償却/減価償却/減損 | E32: Amort./deprec.imobilizados | F32: 固定资产摊销/折旧/减值
... A38: 513000 | B38: Reduction in general bad debt allowance | C38: Verminderung der Pauschalwertberichtigungen | D38: 一般貸倒引当金の減額 | E38: Redução em provisão geral créditos irrecuperáveis | F38: 常规坏账准备扣减
A39: 58000D | B39: Clearing account - Other operating | C39: Verrechnungskonto - Sonstiges Betriebsergebnis | D39: 消込勘定 - その他営業 | E39: Conta de compensação - outro resultado operacional | F39: 清账科目 - 其他运营
A40: 512000 | B40: Gains on the sale of shares | C40: Erträge aus dem Verkauf von Anteilen | D40: 株式売却益 | E40: Ganhos da venda de participações | F40: 股份卖出收益
A41: 314600 | B41: Recyclable fair value reserve, before tax | C41: Wiederverwendbare Zeitwertrücklage, vor Steuern | D41: 税引き前再利用時価準備金 | E41: Reserva val.atual reutilizável, anterior a imposto | F41: 可回收公允价值准备金，税前
A42: 262100 | B42: Warranty provision, Non-current | C42: Garantierückstellung, langfristig | D42: 非流動保証引当金 | E42: Provisão de garantia, longo prazo | F42: 非流动担保准备金
A43: 261100 | B43: Provisions for employee benefits, Non-current | C43: Rückst. für Leistungen an Arbeitnehmer, langfr. | D43: 従業員給付の非流動引当金 | E43: Provisões para benefícios empregado, longo prazo | F43: 非流动员工福利准备金
A44: 251000 | B44: Liabilities included in disposal groups HFS | C44: Verbindl. in Veräußerungsgruppen zur Veräußerung | D44: 処分グループ HFS に含まれる負債 | E44: Obrigs.incls.grupos alien.previstos p/alienação | F44: 处置组 HFS 中包括的负债
A45: 27100D | B45: Clearing account - Financial assets/liab, N-Curr | C45: VerrechKto - Fin. Vermögenswerte/Verbind., langfr. | D45: 消込勘定 - 非流動金融資産/負債 | E45: Conta compensação - imobs./passivos fins., LPrazo | F45: 清算科目 - 非流动财务资产/负债
A46: 242600 | B46: Miscellaneous provisions, Current | C46: Sonstige Rückstellungen, kurzfristig | D46: その他流動引当金 | E46: Provisões neutras, curto prazo | F46: 流动杂项准备金
A47: 242500 | B47: Prov - decommission/restor/rehab. costs, Current | C47: RüSt. - Aufw. Entsorg./Wiederherstell./Sanier., KF | D47: 引当金 - 流動廃止/復元/再生費用 | E47: Prov.- desativação/restaur./csts.reabil., crt.prz. | F47: 准备金 - 流动停用/恢复/复原成本
A48: 242400 | B48: Onerous contracts provision, Current | C48: Rückstellung für belastende Verträge, kurzfristig | D48: 流動有償契約引当金 | E48: Provisão de contratos onerosos, curto prazo | F48: 流动有偿合同准备金
A49: 242300 | B49: Legal proceedings provision, Current | C49: Prozessrückstellung, kurzfristig | D49: 流動法的手段引当金 | E49: Provisão de ações civis, curto prazo | F49: 流动法律程序准备金
A50: 242200 | B50: Restructuring provision, Current | C50: Restrukturierungsrückstellung, kurzfristig | D50: 流動再構成引当金 | E50: Provisão de reestruturação, curto prazo | F50: 流动重组准备金
A51: 242100 | B51: Warranty provision, Current | C51: Garantierückstellung, kurzfristig | D51: 流動保証引当金 | E51: Provisão de garantia, curto prazo | F51: 流动担保准备金
A52: 241100 | B52: Provisions for employee benefits, Current | C52: Rückst. für Leistungen an Arbeitnehmer, kurzfr. | D52: 従業員給付の流動引当金 | E52: Provisões para benefícios empregado, curto prazo | F52: 流动员工福利准备金
A53: 221600 | B53: Other financial liabilities, Current | C53: Sonstige finanzielle Verbindlichkeiten, kurzfr. | D53: その他流動金融負債 | E53: Outros passivos financeiros, curto prazo | F53: 其他流动金融负债
A54: 221500 | B54: Bank overdrafts, classified as cash equivalents | C54: Kontokorrentkredite, als Zahlmtteläquiv. klassif. | D54: 現金同等物に分類された銀行当座貸越 | E54: Descobs.ctas.bancs., classifs.como recursos líqs. | F54: 按现金等价物分类的银行透支
A55: 221400 | B55: Derivatives, Current | C55: Derivate, kurzfristig | D55: 流動デリバティブ | E55: Derivativos, curto prazo | F55: 流动衍生品
A56: 221300 | B56: Convertible bonds, Current | C56: Konvertible Anleihen, kurzfristig | D56: 流動転換社債 | E56: Títulos conversíveis, curto prazo | F56: 流动可兑换债券
A57: 221200 | B57: Finance leases, Current | C57: Finanzierungsleasing, kurzfristig | D57: 流動ファイナンスリース | E57: Arrendamentos financeiros, curto prazo | F57: 流动融资租赁
... A81: 281500 | B81: Debts on purchase of inv / other assets, N-Current | C81: Verbindl. aus Erwerb von Btlg./so. VermW., langfr. | D81: 棚卸資産/その他資産の購入に対する非流動債務 | E81: Dívidas compra invest./outros imobs., longo prazo | F81: 采购其他资产投资的非流动债务
A82: S00001 | B82: Group Shares (%) | C82: Kreisanteile (%) | D82: グループ持分 (%) | E82: Participações do grupo (%) | F82: 集团股份 (%)
A83: 281400 | B83: Debts on purchase / inv. in oth. entities, N-Curr | C83: Verb. aus Erwerb v. Btlg. an so. Einheiten, langfr | D83: その他エンティティの購入/投資に対する非流動債務 | E83: Dívidas compra/invest.outras ents., longo prazo | F83: 采购其他实体投资的非流动债务
A84: 281300 | B84: Debts on purchase of inv. in subs., N-Current | C84: Verbindl. aus Erwerb v. Btlg. an Tochter, langfr. | D84: 子会社への棚卸資産の購入に対する非流動債務 | E84: Dívidas compra invest.subsid., longo prazo | F84: 采购子公司投资的非流动债务
A85: 281200 | B85: Debts on purchase of intangible assets, N-Current | C85: Verbind. aus Erwerb von imm. VermögGgnst., langfr. | D85: 無形資産の購入に対する非流動債務 | E85: Dívidas na compra imobs.intangíveis, longo prazo | F85: 采购无形资产的非流动债务
A86: 281100 | B86: Debts on purchase of PPE, N-Current | C86: Verbindlichk. aus Erwerb von Sachanlagen, langfr. | D86: PPE の購入に対する非流動債務 | E86: Dívidas na compra de bens mats., longo prazo | F86: 采购物业、工厂与设备的非流动债务
A87: 271500 | B87: Other financial liabilities, Non-current | C87: Sonstige finanzielle Verbindlichkeiten, langfr. | D87: その他非流動金融負債 | E87: Outros passivos financeiros, longo prazo | F87: 其他非流动金融负债
A88: 271400 | B88: Derivatives, Non-current | C88: Derivate, langfristig | D88: 非流動デリバティブ | E88: Derivativos, longo prazo | F88: 非流动衍生品
A89: 271300 | B89: Convertible bonds, Non-current | C89: Konvertible Anleihen, langfristig | D89: 非流動転換社債 | E89: Títulos conversíveis, longo prazo | F89: 非流动可兑换债券
A90: 271200 | B90: Finance leases, Non-current | C90: Finanzierungsleasing, langfristig | D90: 非流動ファイナンスリース | E90: Arrendamentos financeiros, longo prazo | F90: 非流动融资租赁
A91: 271100 | B91: Borrowings, Non-current | C91: Fremdmittelaufnahme, langfristig | D91: 非流動借入 | E91: Empréstimos, longo prazo | F91: 非流动借款
A92: 262600 | B92: Miscellaneous provisions, Non-current | C92: Sonstige Rückstellungen, langfristig | D92: その他非流動引当金 | E92: Provisões neutras, longo prazo | F92: 非流动杂项准备金
A93: 262500 | B93: Prov - decommission/restor/rehab. costs, N-Current | C93: RüSt. - Aufw. Entsorg./Wiederherstell./Sanier., LF | D93: 引当金 - 非流動廃止/復元/再生費用 | E93: Prov.- desativação/restaur./csts.reabil., lng.prz. | F93: 准备金 - 非流动停用/恢复/复原成本
A94: 262400 | B94: Onerous contracts provision, Non-current | C94: Rückstellung für belastende Verträge, langfristig | D94: 非流動有償契約引当金 | E94: Provisão de contratos onerosos, longo prazo | F94: 非流动有偿合同准备金
A95: 28100D | B95: Clearing account - Receiv./payables, Non-current | C95: Verrechnungskonto - Ford./Verbindl., langfristig | D95: 消込勘定 - 非流動債権/債務 | E95: Cta.compensação - créditos/obrigações, longo prazo | F95: 清算科目 - 非流动应收账款/应付账款
A96: 262300 | B96: Legal proceedings provision, Non-current | C96: Prozessrückstellung, langfristig | D96: 非流動法的手段引当金 | E96: Provisão de ações civis, longo prazo | F96: 非流动法律程序准备金
A97: 262200 | B97: Restructuring provision, Non-current | C97: Restrukturierungsrückstellung, langfristig | D97: 非流動再構成引当金 | E97: Provisão de reestruturação, longo prazo | F97: 非流动重组准备金
A98: X13009 | B98: IC Other Rec Current | C98: Intern - sonstige Forderungen, kurzfristig | D98: IC その他流動債権 | E98: Outros créditos IE curto prazo
A99: X13008 | B99: IC Trade Payables | C99: Intern - Verbindlichkeiten aus LuL | D99: 会社間支払債務 | E99: Obrigações comerciais IE
A100: X13007 | B100: IC Trade Receivable | C100: Intern - Forderungen aus Lief. u. Leist. | D100: 会社間売上債権 | E100: Créditos comerciais IE
A101: X13006 | B101: Rendering services | C101: Erbringung von Dienstleistungen | D101: 実施サービス | E101: Prestação de serviços
A102: X13005 | B102: Sale of goods | C102: Verkauf von Gütern | D102: 商品販売 | E102: Venda de mercadorias
A103: X13004 | B103: PL IC Financial exp | C103: GuV - interne Finanzaufwendungen | D103: PL IC 財務費用 | E103: Resultado despesas financeiras IE
A104: X13003 | B104: PL IC Financial inc | C104: GuV - interne Finanzerträge | D104: PL IC 財務収益 | E104: Resultado rendimento financeiro IE
A105: X13002 | B105: PL IC Expense 1 | C105: GuV - interner Aufwand 1 | D105: 損益会社間費用 1 | E105: Resultado despesa IE 1
A106: X13001 | B106: PL IC OP income | C106: GuV - interne betriebliche Erträge | D106: 損益会社間営業収益 | E106: Resultado operacional IE
A107: X13000 | B107: Interunit Elimination | C107: Konzernaufrechnung | D107: 内部取引消去 | E107: Eliminações de consolidação
A108: X11004 | B108: Annual net income in BS and IS | C108: Jahresüberschuss in Bilanz und GuV | D108: BS および IS の当期純利益 | E108: Lucro líquido do exercício no balanço e DRE | F108: BS 和 IS 中的年度净收入
A109: X11003 | B109: P&L FS items translated @ average rate | C109: GuV-Positionen zum Mittelkurs umgerechnet | D109: 平均値で換算された P&L 連結勘定科目 | E109: Itens DRE convertidos @ taxa média | F109: 损益财务报表项目已按平均费率换算
A110: X11002 | B110: B/S FS items translated @ historical conversion | C110: Bilanzpositionen zum historischen Kurs umgerechnet | D110: 履歴換算で換算された B/S 連結勘定科目 | E110: Itens DRE balanço convertidos @ conversão hist. | F110: B/S 财务报表项目使用历史转换率换算
A111: X11001 | B111: B/S items translated @ closing rate | C111: Bilanzpositionen zum Schlusskurs umgerechnet | D111: 終値で換算された B/S 明細 | E111: Itens balanço convertidos @ cotação fechamento | F111: B/S 项目使用收盘汇率换算
A112: 799000 | B112: Net income/loss | C112: Jahresüberschuss/Jahresfehlbetrag | D112: 当期損益 | E112: Lucro/déficit líquido do exercício | F112: 净收入/损失
A113: 319000 | B113: Net income - clearing | C113: Jahresüberschuss - Verrechnung | D113: 当期利益 - 消込 | E113: Lucro líquido do exercício - compensação | F113: 净收入 - 清算
A114: 799999 | B114: Secondary cost element | C114: Sekundärkostenart | D114: 二次原価要素 | E114: Classe de custo secundário | F114: 次要成本要素
A115: 314100 | B115: Remeasurements of defined benefit plans, bef. tax | C115: Neubewertung von leistungsorient. Plänen, vor St. | D115: 税引き前福利プランの再測定 | E115: Reavaliações planos benefícios defs., antes imps. | F115: 重估已定义福利计划，税前
A116: 792000 | B116: Net income - NCI | C116: Jahresüberschuss - Minderheitenanteil | D116: 当期利益 - NCI | E116: Lucro líquido do exercício - interesse minoritário | F116: 净收入 - 少数股东权益
A117: 730000 | B117: Profit (loss) from discontinued operations | C117: Gewinn (Verlust) aus aufgegeb. Geschäftsbereichen | D117: 非継続事業の損益 | E117: Lucro (perda) de suspensão da atividade comercial | F117: 非持续经营的利润（损失）
A118: 722000 | B118: Deferred tax | C118: Latente Steuern | D118: 繰延税金 | E118: Impostos diferidos | F118: 递延税
A119: 721000 | B119: Income tax | C119: Ertragsteuer | D119: 所得税 | E119: Imposto de renda | F119: 所得税
A120: 711000 | B120: Share of profit - associates / JV at equity method | C120: Gewinnanteil - assoz. Unt., JV nach Equity-Methode | D120: 利益分配 - 関連会社/JV (持分法) | E120: Partic.lucros - emprs.assocs./JV em equiv.patrim. | F120: 利润份额 - 关联/JV（权益方法）
A121: 653000 | B121: Other financial expenses | C121: Sonstige Finanzaufwendungen | D121: その他財務費用 | E121: Outras despesas financeiras | F121: 其他金融费用
A122: 652000 | B122: Interest expenses | C122: Zinsaufwendungen | D122: 支払利息 | E122: Gastos com juros | F122: 利息费用
A123: 651000 | B123: Allowances (reversals) for provisions on shares | C123: Wertbericht. (Auflösung) für Rückstll. zu Anteilen | D123: 持分引当金の引当金 (取消) | E123: Fundos reserva (estornos) para provisões ações | F123: 每股准备金的补贴（冲销）
A124: 65400D | B124: Clearing account - financial result | C124: Verrechnungskonto - Finanzergebnis | D124: 消込勘定 - 財務結果 | E124: Conta de compensação - resultado financeiro | F124: 清账科目 - 财务结果
A125: X14000 | B125: Investments / Equity consolidation | C125: Beteiligungen/Equitykonsolidierung | D125: 投資/資本連結 | E125: Investimentos/equivalência patrimonial
A126: X14112 | B126: Share of OCI & other movements - EM (loc | C126: Anteil am so. Gsmterg. u. an so. Bew. - EM (lok.) | D126: OCI およびその他移動の持分 - EM (ローカル) | E126: Participação OCI & outros movimentos - EP (loc.)
A127: X14111 | B127: Equity component of compound financial i | C127: Eigenkapitalkomp. von zusammengesetzten FinInstr. | D127: 複合金融商品の資本要素 | E127: Componente patrim.líq.instrs.financeiros compostos
A128: X14110 | B128: Income tax on foreign currency translati | C128: Ertragsteuer auf Währungsumrechnungsrücklage | D128: 外貨換算の所得税 | E128: Imposto de renda sobre conversão moeda estrangeira
A129: X14109 | B129: Foreign currency translation reserve, be | C129: Währungsumrechnungsrücklage, vor Steuern | D129: 外貨換算準備金 | E129: Reserva conv.moeda estrangeira, antes impostos
...
