Workbook

Sheet Balance 2023.12
A1: Language/ Sprache/ 言語/ Linguagem >>> | B1: English | C1: =MATCH(B1, H3:L3,0) -> 1
A3: E | B3: Measures | C3: Amount in Group Crcy | H3: English | I3: Deutsch | J3: 日本語 | K3: Portugues | L3: 中文
A4: FS Item | B4: FS Item | C4: J10 | D4: J1R | E4: J20 | F4: J2R
A5: 111100 | B5: =VLOOKUP(A5,Sheet2!A:F,1+'Balance 2023.12'!C$1,FALSE) -> Cash on hand | C5: 17278224 | D5: 17278224 | E5: 24046108 | F5: 24046108
A6: 111200 | B6: =VLOOKUP(A6,Sheet2!A:F,1+'Balance 2023.12'!C$1,FALSE) -> Short-term deposits and other cash equivalents | C6: 8057775.2 | D6: 8057775.2 | E6: 11214008 | F6: 11214008
A7: 121100 | B7: =VLOOKUP(A7,Sheet2!A:F,1+'Balance 2023.12'!C$1,FALSE) -> Trade receivables, Gross | C7: 27016242 | D7: 27026921 | E7: 37598510 | F7: 37613371
A8: 121190 | B8: =VLOOKUP(A8,Sheet2!A:F,1+'Balance 2023.12'!C$1,FALSE) -> Trade receivables, Allowance | C8: -931550.74 | D8: -931550.74 | E8: -1296439.4 | F8: -1296439.4
A9: 121200 | B9: =VLOOKUP(A9,Sheet2!A:F,1+'Balance 2023.12'!C$1,FALSE) -> Receivables on disposal of PPE, Current, Gross | C9: 8519.82 | D9: 8519.82 | E9: 11857.03 | F9: 11857.03
A10: 121300 | B10: =VLOOKUP(A10,Sheet2!A:F,1+'Balance 2023.12'!C$1,FALSE) -> Receivables / disp. Intang.assets, Current, Gross | C10: 5679.88 | D10: 5679.88 | E10: 7904.69 | F10: 7904.69
A11: 121400 | B11: =VLOOKUP(A11,Sheet2!A:F,1+'Balance 2023.12'!C$1,FALSE) -> Receivables / disp. invest. subsid, Current, Gross | C11: 1324.84 | D11: 1324.84 | E11: 1843.78 | F11: 1843.78
A12: 121500 | B12: =VLOOKUP(A12,Sheet2!A:F,1+'Balance 2023.12'!C$1,FALSE) -> Receivables / disp. Inv. oth entities, Current, GV | C12: 3974.51 | D12: 3974.51 | E12: 5531.33 | F12: 5531.33
A13: 121600 | B13: =VLOOKUP(A13,Sheet2!A:F,1+'Balance 2023.12'!C$1,FALSE) -> Receivables /disp. Inv. oth assets, Current, Gross | C13: 2839.94 | D13: 2839.94 | E13: 3952.35 | F13: 3952.35
A14: 121700 | B14: =VLOOKUP(A14,Sheet2!A:F,1+'Balance 2023.12'!C$1,FALSE) -> Dividends receivable | C14: 1500 | D14: 1500 | E14: 2087.55 | F14: 2087.55
A15: 121800 | B15: =VLOOKUP(A15,Sheet2!A:F,1+'Balance 2023.12'!C$1,FALSE) -> Other receivables, Current, Gross | C15: 678279.37 | D15: 678279.37 | E15: 943961.54 | F15: 943961.54
A16: 121900 | B16: =VLOOKUP(A16,Sheet2!A:F,1+'Balance 2023.12'!C$1,FALSE) -> Accrued interests on receivables | C16: 48278.95 | D16: 48278.95 | E16: 67189.82 | F16: 67189.82
... A163: 799000 | B163: =VLOOKUP(A163,Sheet2!A:F,1+'Balance 2023.12'!C$1,FALSE) -> Net income/loss | C163: 22090605 | D163: 22092426 | E163: 32497223 | F163: 32499901
A164: 13100D | B164: =VLOOKUP(A164,Sheet2!A:F,1+'Balance 2023.12'!C$1,FALSE) -> Clearing Account - Gross Margin B/S | C164: 0 | D164: 0 | E164: 0 | F164: 0
A165: 1721HC | B165: =VLOOKUP(A165,Sheet2!A:F,1+'Balance 2023.12'!C$1,FALSE) -> Elimination of investment, held cons unit | C165: -1612000 | D165: -1612000 | E165: -2370607.2 | F165: -2370607.2
A166: 1721OC | B166: =VLOOKUP(A166,Sheet2!A:F,1+'Balance 2023.12'!C$1,FALSE) -> Elimination of investment, owner cons unit | C166: 1612000 | D166: 1612000 | E166: 2370607.2 | F166: 2370607.2
A167: 21100D | B167: =VLOOKUP(A167,Sheet2!A:F,1+'Balance 2023.12'!C$1,FALSE) -> Clearing account - Receivables/payables, Current | C167: 0 | D167: 0 | E167: 0 | F167: 0
A168: 21110D | B168: =VLOOKUP(A168,Sheet2!A:F,1+'Balance 2023.12'!C$1,FALSE) -> Clearing account - Trade Rec/Pay, Current | C168: 0 | D168: 0 | E168: 0 | F168: 0
A169: 21170D | B169: =VLOOKUP(A169,Sheet2!A:F,1+'Balance 2023.12'!C$1,FALSE) -> Clearing - Dividends rec/pay, Current | C169: 0 | D169: 0 | E169: 0 | F169: 0
A170: 22100D | B170: =VLOOKUP(A170,Sheet2!A:F,1+'Balance 2023.12'!C$1,FALSE) -> Clearing account - Financial assets/liab, Current | C170: 0 | D170: 0 | E170: 0 | F170: 0
A171: 28100D | B171: =VLOOKUP(A171,Sheet2!A:F,1+'Balance 2023.12'!C$1,FALSE) -> Clearing account - Receiv./payables, Non-current | C171: 0 | D171: 0 | E171: 0 | F171: 0
A172: 41200D | B172: =VLOOKUP(A172,Sheet2!A:F,1+'Balance 2023.12'!C$1,FALSE) -> Clearing account - Gross margin | C172: 0 | D172: 0 | E172: 0 | F172: 0
A173: 58000D | B173: =VLOOKUP(A173,Sheet2!A:F,1+'Balance 2023.12'!C$1,FALSE) -> Clearing account - Other operating | C173: 0 | D173: 0 | E173: 0.01 | F173: 0.01
A174: 65400D | B174: =VLOOKUP(A174,Sheet2!A:F,1+'Balance 2023.12'!C$1,FALSE) -> Clearing account - financial result | C174: 0 | D174: 0 | E174: -0.01 | F174: -0.01

Sheet Balance Sheet 2023.12
A1: Language/ Sprache/ 言語/ Linguagem >>> | B1: English | C1: =MATCH(B1, H3:L3,0) -> 1
B3: Measures | C3: Sign-Adjusted Amount in Group Crcy | H3: English | I3: Deutsch | J3: 日本語 | K3: Portugues | L3: 中文
A4: FS Item | C4: J10 | D4: J1R | E4: J20 | F4: J2R
A5: Y1/BS/BS | B5: =VLOOKUP(A5,Sheet2!A:F,1+'Balance Sheet 2023.12'!C$1,FALSE) -> Balance Sheet | C5: 0 | D5: 0 | E5: 0 | F5: 0
A6: Y1/BS/TA0000 | B6: =VLOOKUP(A6,Sheet2!A:F,1+'Balance Sheet 2023.12'!C$1,FALSE) -> Assets | C6: 80471832 | D6: 80481211 | E6: 1.1199267e+08 | F6: 1.1200572e+08
A7: Y1/BS/TAC000 | B7: =VLOOKUP(A7,Sheet2!A:F,1+'Balance Sheet 2023.12'!C$1,FALSE) -> Current assets | C7: 58389764 | D7: 58400442 | E7: 81261046 | F7: 81275908
A8: Y1/BS/TAC100 | B8: =VLOOKUP(A8,Sheet2!A:F,1+'Balance Sheet 2023.12'!C$1,FALSE) -> Current assets oth.than incl.in disposal groups | C8: 58387764 | D8: 58398442 | E8: 81258263 | F8: 81273125
A9: Y1/BS/T11100 | B9: =VLOOKUP(A9,Sheet2!A:F,1+'Balance Sheet 2023.12'!C$1,FALSE) -> Cash and cash equivalents | C9: 25335999 | D9: 25335999 | E9: 35260116 | F9: 35260116
A10: 111100 | B10: =VLOOKUP(A10,Sheet2!A:F,1+'Balance Sheet 2023.12'!C$1,FALSE) -> Cash on hand | C10: 17278224 | D10: 17278224 | E10: 24046108 | F10: 24046108
A11: 111200 | B11: =VLOOKUP(A11,Sheet2!A:F,1+'Balance Sheet 2023.12'!C$1,FALSE) -> Short-term deposits and other cash equivalents | C11: 8057775.2 | D11: 8057775.2 | E11: 11214008 | F11: 11214008
A12: Y1/BS/T12100 | B12: =VLOOKUP(A12,Sheet2!A:F,1+'Balance Sheet 2023.12'!C$1,FALSE) -> Trade and other current receivables | C12: 26815209 | D12: 26825888 | E12: 37318732 | F12: 37333594
A13: 121100 | B13: =VLOOKUP(A13,Sheet2!A:F,1+'Balance Sheet 2023.12'!C$1,FALSE) -> Trade receivables, Gross | C13: 27016242 | D13: 27026921 | E13: 37598510 | F13: 37613371
A14: 121190 | B14: =VLOOKUP(A14,Sheet2!A:F,1+'Balance Sheet 2023.12'!C$1,FALSE) -> Trade receivables, Allowance | C14: -931550.74 | D14: -931550.74 | E14: -1296439.4 | F14: -1296439.4
A15: 121200 | B15: =VLOOKUP(A15,Sheet2!A:F,1+'Balance Sheet 2023.12'!C$1,FALSE) -> Receivables on disposal of PPE, Current, Gross | C15: 8519.82 | D15: 8519.82 | E15: 11857.03 | F15: 11857.03
A16: 121300 | B16: =VLOOKUP(A16,Sheet2!A:F,1+'Balance Sheet 2023.12'!C$1,FALSE) -> Receivables / disp. Intang.assets, Current, Gross | C16: 5679.88 | D16: 5679.88 | E16: 7904.69 | F16: 7904.69
A17: 121400 | B17: =VLOOKUP(A17,Sheet2!A:F,1+'Balance Sheet 2023.12'!C$1,FALSE) -> Receivables / disp. invest. subsid, Current, Gross | C17: 1324.84 | D17: 1324.84 | E17: 1843.78 | F17: 1843.78
A18: 121500 | B18: =VLOOKUP(A18,Sheet2!A:F,1+'Balance Sheet 2023.12'!C$1,FALSE) -> Receivables / disp. Inv. oth entities, Current, GV | C18: 3974.51 | D18: 3974.51 | E18: 5531.33 | F18: 5531.33
A19: 121600 | B19: =VLOOKUP(A19,Sheet2!A:F,1+'Balance Sheet 2023.12'!C$1,FALSE) -> Receivables /disp. Inv. oth assets, Current, Gross | C19: 2839.94 | D19: 2839.94 | E19: 3952.35 | F19: 3952.35
A20: 121700 | B20: =VLOOKUP(A20,Sheet2!A:F,1+'Balance Sheet 2023.12'!C$1,FALSE) -> Dividends receivable | C20: 1500 | D20: 1500 | E20: 2087.55 | F20: 2087.55
A21: 121800 | B21: =VLOOKUP(A21,Sheet2!A:F,1+'Balance Sheet 2023.12'!C$1,FALSE) -> Other receivables, Current, Gross | C21: 678279.37 | D21: 678279.37 | E21: 943961.54 | F21: 943961.54
A22: 121900 | B22: =VLOOKUP(A22,Sheet2!A:F,1+'Balance Sheet 2023.12'!C$1,FALSE) -> Accrued interests on receivables | C22: 48278.95 | D22: 48278.95 | E22: 67189.82 | F22: 67189.82
A23: 121990 | B23: =VLOOKUP(A23,Sheet2!A:F,1+'Balance Sheet 2023.12'!C$1,FALSE) -> Other receivables, Allow | C23: -19879.57 | D23: -19879.57 | E23: -27666.4 | F23: -27666.4
A24: Y1/BS/T12300 | B24: =VLOOKUP(A24,Sheet2!A:F,1+'Balance Sheet 2023.12'!C$1,FALSE) -> Other current assets | C24: 49494.5 | D24: 49494.5 | E24: 68881.51 | F24: 68881.51
A25: 123100 | B25: =VLOOKUP(A25,Sheet2!A:F,1+'Balance Sheet 2023.12'!C$1,FALSE) -> Prepaid expenses | C25: 49494.5 | D25: 49494.5 | E25: 68881.51 | F25: 68881.51
A26: Y1/BS/T13100 | B26: =VLOOKUP(A26,Sheet2!A:F,1+'Balance Sheet 2023.12'!C$1,FALSE) -> Inventories | C26: 6127657.6 | D26: 6127657.6 | E26: 8527862.1 | F26: 8527862.1
A27: 131100 | B27: =VLOOKUP(A27,Sheet2!A:F,1+'Balance Sheet 2023.12'!C$1,FALSE) -> Raw materials | C27: 2194399.5 | D27: 2194399.5 | E27: 3053946.2 | F27: 3053946.2
A28: 131200 | B28: =VLOOKUP(A28,Sheet2!A:F,1+'Balance Sheet 2023.12'!C$1,FALSE) -> Merchandise | C28: 2568881.8 | D28: 2568881.8 | E28: 3575113.2 | F28: 3575113.2
A29: 131300 | B29: =VLOOKUP(A29,Sheet2!A:F,1+'Balance Sheet 2023.12'!C$1,FALSE) -> Production supplies | C29: 2271.96 | D29: 2271.96 | E29: 3161.88 | F29: 3161.88
A30: 131400 | B30: =VLOOKUP(A30,Sheet2!A:F,1+'Balance Sheet 2023.12'!C$1,FALSE) -> Work in progress | C30: 674933.05 | D30: 674933.05 | E30: 939304.45 | F30: 939304.45
A31: 131500 | B31: =VLOOKUP(A31,Sheet2!A:F,1+'Balance Sheet 2023.12'!C$1,FALSE) -> Finished goods | C31: 685751.33 | D31: 685751.33 | E31: 954360.24 | F31: 954360.24
A32: 131600 | B32: =VLOOKUP(A32,Sheet2!A:F,1+'Balance Sheet 2023.12'!C$1,FALSE) -> Other inventories | C32: 1419.98 | D32: 1419.98 | E32: 1976.17 | F32: 1976.17
A33: 13100D | B33: =VLOOKUP(A33,Sheet2!A:F,1+'Balance Sheet 2023.12'!C$1,FALSE) -> Clearing Account - Gross Margin B/S | C33: 0 | D33: 0 | E33: 0 | F33: 0
A34: Y1/BS/T14100 | B34: =VLOOKUP(A34,Sheet2!A:F,1+'Balance Sheet 2023.12'!C$1,FALSE) -> Other current financial assets | C34: 59403.22 | D34: 59403.22 | E34: 82671.46 | F34: 82671.46
A35: 141100 | B35: =VLOOKUP(A35,Sheet2!A:F,1+'Balance Sheet 2023.12'!C$1,FALSE) -> Other financial assets at FVTOCI, Current | C35: 20515.85 | D35: 20515.85 | E35: 28551.91 | F35: 28551.91
A36: 141200 | B36: =VLOOKUP(A36,Sheet2!A:F,1+'Balance Sheet 2023.12'!C$1,FALSE) -> Derivatives, Current | C36: 10456 | D36: 10456 | E36: 14551.61 | F36: 14551.61
A37: 141300 | B37: =VLOOKUP(A37,Sheet2!A:F,1+'Balance Sheet 2023.12'!C$1,FALSE) -> Financial assets at FVPL, Current | C37: 5711.86 | D37: 5711.86 | E37: 7949.2 | F37: 7949.2
A38: 141400 | B38: =VLOOKUP(A38,Sheet2!A:F,1+'Balance Sheet 2023.12'!C$1,FALSE) -> Loans and cash advances, Current, Gross | C38: 31239.32 | D38: 31239.32 | E38: 43475.77 | F38: 43475.77
A39: 141490 | B39: =VLOOKUP(A39,Sheet2!A:F,1+'Balance Sheet 2023.12'!C$1,FALSE) -> Loans and cash advances, Current, Allowance | C39: -8519.81 | D39: -8519.81 | E39: -11857.03 | F39: -11857.03
A40: Y1/BS/TAC200 | B40: =VLOOKUP(A40,Sheet2!A:F,1+'Balance Sheet 2023.12'!C$1,FALSE) -> NC assets or disp. groups classified HFS/HDO | C40: 2000 | D40: 2000 | E40: 2783.4 | F40: 2783.4
A41: 151100 | B41: =VLOOKUP(A41,Sheet2!A:F,1+'Balance Sheet 2023.12'!C$1,FALSE) -> NC assets or disp. groups classified HFS | C41: 2000 | D41: 2000 | E41: 2783.4 | F41: 2783.4
A42: Y1/BS/TANC00 | B42: =VLOOKUP(A42,Sheet2!A:F,1+'Balance Sheet 2023.12'!C$1,FALSE) -> Non Current assets | C42: 22082068 | D42: 22080768 | E42: 30731619 | F42: 30729810
A43: Y1/BS/T16100 | B43: =VLOOKUP(A43,Sheet2!A:F,1+'Balance Sheet 2023.12'!C$1,FALSE) -> Property, plant and equipment | C43: 16676313 | D43: 16676313 | E43: 23208428 | F43: 23208428
A44: 161100 | B44: =VLOOKUP(A44,Sheet2!A:F,1+'Balance Sheet 2023.12'!C$1,FALSE) -> Lands and buildings | C44: 22252278 | D44: 22252278 | E44: 30968499 | F44: 30968499
A45: 161190 | B45: =VLOOKUP(A45,Sheet2!A:F,1+'Balance Sheet 2023.12'!C$1,FALSE) -> Lands and buildings, Depreciation | C45: -7107184.5 | D45: -7107184.5 | E45: -9891070 | F45: -9891070
A46: 161200 | B46: =VLOOKUP(A46,Sheet2!A:F,1+'Balance Sheet 2023.12'!C$1,FALSE) -> Tangibles assets under construction | C46: 1102669.8 | D46: 1102669.8 | E46: 1534585.8 | F46: 1534585.8
A47: 161300 | B47: =VLOOKUP(A47,Sheet2!A:F,1+'Balance Sheet 2023.12'!C$1,FALSE) -> Office equipment | C47: 229332.65 | D47: 229332.65 | E47: 319162.32 | F47: 319162.32
A48: 161390 | B48: =VLOOKUP(A48,Sheet2!A:F,1+'Balance Sheet 2023.12'!C$1,FALSE) -> Office equipment, Depreciation | C48: -73862.62 | D48: -73862.62 | E48: -102794.61 | F48: -102794.61
A49: 161400 | B49: =VLOOKUP(A49,Sheet2!A:F,1+'Balance Sheet 2023.12'!C$1,FALSE) -> Vehicles | C49: 73838.39 | D49: 73838.39 | E49: 102760.91 | F49: 102760.91
A50: 161490 | B50: =VLOOKUP(A50,Sheet2!A:F,1+'Balance Sheet 2023.12'!C$1,FALSE) -> Vehicles, Depreciation | C50: -51118.89 | D50: -51118.89 | E50: -71142.17 | F50: -71142.17
A51: 161500 | B51: =VLOOKUP(A51,Sheet2!A:F,1+'Balance Sheet 2023.12'!C$1,FALSE) -> Machinery | C51: 50550.89 | D51: 50550.89 | E51: 70351.71 | F51: 70351.71
A52: 161590 | B52: =VLOOKUP(A52,Sheet2!A:F,1+'Balance Sheet 2023.12'!C$1,FALSE) -> Machinery, Depreciation | C52: -21469.92 | D52: -21469.92 | E52: -29879.71 | F52: -29879.71
A53: 161600 | B53: =VLOOKUP(A53,Sheet2!A:F,1+'Balance Sheet 2023.12'!C$1,FALSE) -> Other property, plant and equipment | C53: 631650.43 | D53: 631650.43 | E53: 879068.05 | F53: 879068.05
A54: 161690 | B54: =VLOOKUP(A54,Sheet2!A:F,1+'Balance Sheet 2023.12'!C$1,FALSE) -> Other property, plant and equipment, Depreciation | C54: -410371.02 | D54: -410371.02 | E54: -571113.5 | F54: -571113.5
A55: Y1/BS/T16200 | B55: =VLOOKUP(A55,Sheet2!A:F,1+'Balance Sheet 2023.12'!C$1,FALSE) -> Investment property | C55: 90452.02 | D55: 90452.02 | E55: 125882.09 | F55: 125882.09
A56: 162100 | B56: =VLOOKUP(A56,Sheet2!A:F,1+'Balance Sheet 2023.12'!C$1,FALSE) -> Investment property | C56: 108485.62 | D56: 108485.62 | E56: 150979.48 | F56: 150979.48
A57: 162190 | B57: =VLOOKUP(A57,Sheet2!A:F,1+'Balance Sheet 2023.12'!C$1,FALSE) -> Investment property, Depreciation | C57: -18033.6 | D57: -18033.6 | E57: -25097.39 | F57: -25097.39
A58: Y1/BS/T16300 | B58: =VLOOKUP(A58,Sheet2!A:F,1+'Balance Sheet 2023.12'!C$1,FALSE) -> Goodwill | C58: 356634.3 | D58: 356634.3 | E58: 496328.63 | F58: 496328.63
A59: 163100 | B59: =VLOOKUP(A59,Sheet2!A:F,1+'Balance Sheet 2023.12'!C$1,FALSE) -> Goodwill | C59: 356634.3 | D59: 356634.3 | E59: 496328.63 | F59: 496328.63
A60: Y1/BS/T16400 | B60: =VLOOKUP(A60,Sheet2!A:F,1+'Balance Sheet 2023.12'!C$1,FALSE) -> Intangible assets | C60: 4380299.6 | D60: 4380299.6 | E60: 6096063.9 | F60: 6096063.9
A61: 164100 | B61: =VLOOKUP(A61,Sheet2!A:F,1+'Balance Sheet 2023.12'!C$1,FALSE) -> Brand names | C61: 494206.16 | D61: 494206.16 | E61: 687786.8 | F61: 687786.8
A62: 164190 | B62: =VLOOKUP(A62,Sheet2!A:F,1+'Balance Sheet 2023.12'!C$1,FALSE) -> Brand names, Amortization | C62: -13460.86 | D62: -13460.86 | E62: -18733.5 | F62: -18733.5
A63: 164200 | B63: =VLOOKUP(A63,Sheet2!A:F,1+'Balance Sheet 2023.12'!C$1,FALSE) -> Computer software | C63: 6692624.1 | D63: 6692624.1 | E63: 9314126.2 | F63: 9314126.2
A64: 164290 | B64: =VLOOKUP(A64,Sheet2!A:F,1+'Balance Sheet 2023.12'!C$1,FALSE) -> Computer software, Amortization | C64: -3170078.9 | D64: -3170078.9 | E64: -4411799.5 | F64: -4411799.5
A65: 164300 | B65: =VLOOKUP(A65,Sheet2!A:F,1+'Balance Sheet 2023.12'!C$1,FALSE) -> Patents, trademarks and other rights | C65: 937179.49 | D65: 937179.49 | E65: 1304273 | F65: 1304273
A66: 164390 | B66: =VLOOKUP(A66,Sheet2!A:F,1+'Balance Sheet 2023.12'!C$1,FALSE) -> Patents, trademarks and other rights, Amortization | C66: -615698.53 | D66: -615698.53 | E66: -856867.86 | F66: -856867.86
A67: 164400 | B67: =VLOOKUP(A67,Sheet2!A:F,1+'Balance Sheet 2023.12'!C$1,FALSE) -> Intangible assets under development | C67: 67306.52 | D67: 67306.52 | E67: 93670.53 | F67: 93670.53
A68: 164490 | B68: =VLOOKUP(A68,Sheet2!A:F,1+'Balance Sheet 2023.12'!C$1,FALSE) -> Intangible assets under development, Impairment | C68: -22719.51 | D68: -22719.51 | E68: -31618.75 | F68: -31618.75
A69: 164500 | B69: =VLOOKUP(A69,Sheet2!A:F,1+'Balance Sheet 2023.12'!C$1,FALSE) -> Other intangible assets | C69: 21938.01 | D69: 21938.01 | E69: 30531.14 | F69: 30531.14
A70: 164590 | B70: =VLOOKUP(A70,Sheet2!A:F,1+'Balance Sheet 2023.12'!C$1,FALSE) -> Other intangible assets, Amortization | C70: -10996.84 | D70: -10996.84 | E70: -15304.32 | F70: -15304.32
A71: Y1/BS/T17100 | B71: =VLOOKUP(A71,Sheet2!A:F,1+'Balance Sheet 2023.12'!C$1,FALSE) -> Investments accounted for using equity method | C71: 84488.04 | D71: 83188.04 | E71: 117582.01 | F71: 115772.8
A72: 171000 | B72: =VLOOKUP(A72,Sheet2!A:F,1+'Balance Sheet 2023.12'!C$1,FALSE) -> Investments accounted for using equity method | C72: 84488.04 | D72: 83188.04 | E72: 117582.01 | F72: 115772.8
A73: Y1/BS/T17200 | B73: =VLOOKUP(A73,Sheet2!A:F,1+'Balance Sheet 2023.12'!C$1,FALSE) -> Other non-current financial assets | C73: 7983.39 | D73: 7983.39 | E73: 11110.49 | F73: 11110.49
A74: 172100 | B74: =VLOOKUP(A74,Sheet2!A:F,1+'Balance Sheet 2023.12'!C$1,FALSE) -> Investments in subs, JV and associates, GV | C74: 0 | D74: 0 | E74: 0 | F74: 0
A75: 1721OC | B75: =VLOOKUP(A75,Sheet2!A:F,1+'Balance Sheet 2023.12'!C$1,FALSE) -> Elimination of investment, owner cons unit | C75: 1612000 | D75: 1612000 | E75: 2370607.2 | F75: 2370607.2
A76: 1721HC | B76: =VLOOKUP(A76,Sheet2!A:F,1+'Balance Sheet 2023.12'!C$1,FALSE) -> Elimination of investment, held cons unit | C76: -1612000 | D76: -1612000 | E76: -2370607.2 | F76: -2370607.2
A77: 172190 | B77: =VLOOKUP(A77,Sheet2!A:F,1+'Balance Sheet 2023.12'!C$1,FALSE) -> Investments in subs, JV and associates, Impair | C77: 0 | D77: 0 | E77: 0 | F77: 0
A78: 172200 | B78: =VLOOKUP(A78,Sheet2!A:F,1+'Balance Sheet 2023.12'!C$1,FALSE) -> Other financial assets at FVTOCI, Non-current | C78: 6171.5 | D78: 6171.5 | E78: 8588.88 | F78: 8588.88
A79: 172400 | B79: =VLOOKUP(A79,Sheet2!A:F,1+'Balance Sheet 2023.12'!C$1,FALSE) -> Financial assets at FVPL, Non-current | C79: 1811.89 | D79: 1811.89 | E79: 2521.61 | F79: 2521.61
A80: Y1/BS/T18100 | B80: =VLOOKUP(A80,Sheet2!A:F,1+'Balance Sheet 2023.12'!C$1,FALSE) -> Non-current receivables | C80: 485897.88 | D80: 485897.88 | E80: 676224.22 | F80: 676224.22
A81: 181100 | B81: =VLOOKUP(A81,Sheet2!A:F,1+'Balance Sheet 2023.12'!C$1,FALSE) -> Loans and cash advances, Non-current, Gross | C81: 289141.84 | D81: 289141.84 | E81: 402398.78 | F81: 402398.78
A82: 181190 | B82: =VLOOKUP(A82,Sheet2!A:F,1+'Balance Sheet 2023.12'!C$1,FALSE) -> Loans and cash advances, Non-current, Allowance | C82: -14199.68 | D82: -14199.68 | E82: -19761.71 | F82: -19761.71
A83: 181200 | B83: =VLOOKUP(A83,Sheet2!A:F,1+'Balance Sheet 2023.12'!C$1,FALSE) -> Receivables on disposal of PPE, N-Current, Gross | C83: 8519.81 | D83: 8519.81 | E83: 11857.03 | F83: 11857.03
A84: 181300 | B84: =VLOOKUP(A84,Sheet2!A:F,1+'Balance Sheet 2023.12'!C$1,FALSE) -> Receiv./ disp. Intang.assets, N-Current, Gross | C84: 2839.94 | D84: 2839.94 | E84: 3952.35 | F84: 3952.35
A85: 181400 | B85: =VLOOKUP(A85,Sheet2!A:F,1+'Balance Sheet 2023.12'!C$1,FALSE) -> Receiv./ disp. invest. subsid, N-Current, Gross | C85: 12000 | D85: 12000 | E85: 16700.4 | F85: 16700.4
A86: 181500 | B86: =VLOOKUP(A86,Sheet2!A:F,1+'Balance Sheet 2023.12'!C$1,FALSE) -> Receiv. / disp. Inv. oth entities, N-Current, GV | C86: 3000 | D86: 3000 | E86: 4175.1 | F86: 4175.1
A87: 181600 | B87: =VLOOKUP(A87,Sheet2!A:F,1+'Balance Sheet 2023.12'!C$1,FALSE) -> Receiv. /disp. Inv. oth assets, N-Current, Gross | C87: 2839.95 | D87: 2839.95 | E87: 3952.35 | F87: 3952.35
A88: 181800 | B88: =VLOOKUP(A88,Sheet2!A:F,1+'Balance Sheet 2023.12'!C$1,FALSE) -> Other receivables, Non-current, Gross | C88: 210155.4 | D88: 210155.4 | E88: 292473.34 | F88: 292473.34
A89: 181890 | B89: =VLOOKUP(A89,Sheet2!A:F,1+'Balance Sheet 2023.12'!C$1,FALSE) -> Receivables, Non-current, Allowance | C89: -28399.38 | D89: -28399.38 | E89: -39523.42 | F89: -39523.42
A90: Y1/BS/T18200 | B90: =VLOOKUP(A90,Sheet2!A:F,1+'Balance Sheet 2023.12'!C$1,FALSE) -> Deferred tax assets | C90: 0 | D90: 0 | E90: 0 | F90: 0
A91: 182100 | B91: =VLOOKUP(A91,Sheet2!A:F,1+'Balance Sheet 2023.12'!C$1,FALSE) -> Deferred tax assets | C91: 0 | D91: 0 | E91: 0 | F91: 0
A92: Y1/BS/TLE000 | B92: =VLOOKUP(A92,Sheet2!A:F,1+'Balance Sheet 2023.12'!C$1,FALSE) -> Liabilities & Equity | C92: 80471832 | D92: 80481211 | E92: 1.1199267e+08 | F92: 1.1199267e+08
A93: Y1/BS/TL0000 | B93: =VLOOKUP(A93,Sheet2!A:F,1+'Balance Sheet 2023.12'!C$1,FALSE) -> Liabilities | C93: 41762519 | D93: 41762519 | E93: 58121154 | F93: 58121154
A94: Y1/BS/TLC000 | B94: =VLOOKUP(A94,Sheet2!A:F,1+'Balance Sheet 2023.12'!C$1,FALSE) -> Current liabilities | C94: 23614999 | D94: 23614999 | E94: 32864999 | F94: 32864999
A95: Y1/BS/TLC100 | B95: =VLOOKUP(A95,Sheet2!A:F,1+'Balance Sheet 2023.12'!C$1,FALSE) -> Current liab oth.than incl.in disposal groups | C95: 23613999 | D95: 23613999 | E95: 32863607 | F95: 32863607
A96: Y1/BS/T21100 | B96: =VLOOKUP(A96,Sheet2!A:F,1+'Balance Sheet 2023.12'!C$1,FALSE) -> Trade and other current payables | C96: 16662416 | D96: 16662416 | E96: 23189087 | F96: 23189087
A97: 211100 | B97: =VLOOKUP(A97,Sheet2!A:F,1+'Balance Sheet 2023.12'!C$1,FALSE) -> Trade payables, Current | C97: 16422293 | D97: 16422293 | E97: 22854908 | F97: 22854908
A98: 21110D | B98: =VLOOKUP(A98,Sheet2!A:F,1+'Balance Sheet 2023.12'!C$1,FALSE) -> Clearing account - Trade Rec/Pay, Current | C98: 0 | D98: 0 | E98: 0 | F98: 0
A99: 211200 | B99: =VLOOKUP(A99,Sheet2!A:F,1+'Balance Sheet 2023.12'!C$1,FALSE) -> Debts on purchase of PPE, Current | C99: 1996.32 | D99: 1996.32 | E99: 2778.29 | F99: 2778.29
A100: 211300 | B100: =VLOOKUP(A100,Sheet2!A:F,1+'Balance Sheet 2023.12'!C$1,FALSE) -> Debts on purchase of intangible assets, Current | C100: 4259.91 | D100: 4259.91 | E100: 5928.51 | F100: 5928.51
A101: 211400 | B101: =VLOOKUP(A101,Sheet2!A:F,1+'Balance Sheet 2023.12'!C$1,FALSE) -> Debts on purchase of inv. in subs., Current | C101: 1500 | D101: 1500 | E101: 2087.56 | F101: 2087.56
...

Sheet P&L 2023.12
A1: Language/ Sprache/ 言語/ Linguagem >>> | B1: English | C1: =MATCH(B1, H3:L3,0) -> 1
B3: Measures | C3: Sign-Adjusted Amount in Group Crcy | H3: English | I3: Deutsch | J3: 日本語 | K3: Portugues | L3: 中文
A4: FS Item | B4: FS Item | C4: J10 | D4: J1R | E4: J20 | F4: J2R
A5: Y1/PL/PL | B5: =VLOOKUP(A5,Sheet2!A:F,1+'P&L 2023.12'!C$1,FALSE) -> Profit & Loss Statement | C5: 0 | D5: 0 | E5: 0 | F5: 0
A6: 799000 | B6: =VLOOKUP(A6,Sheet2!A:F,1+'P&L 2023.12'!C$1,FALSE) -> Net income/loss | C6: 22090605 | D6: 22092426 | E6: 32497223 | F6: 32499901
A7: Y1/PL/TNI000 | B7: =VLOOKUP(A7,Sheet2!A:F,1+'P&L 2023.12'!C$1,FALSE) -> NET INCOME / LOSS | C7: 22090605 | D7: 22092426 | E7: 32497223 | F7: 32499901
A8: Y1/PL/TBT000 | B8: =VLOOKUP(A8,Sheet2!A:F,1+'P&L 2023.12'!C$1,FALSE) -> Profit (loss) before tax | C8: 45933363 | D8: 45935444 | E8: 67562879 | F8: 67565940
A9: Y1/PL/TBFT00 | B9: =VLOOKUP(A9,Sheet2!A:F,1+'P&L 2023.12'!C$1,FALSE) -> Profit Before Financing and Income Taxes | C9: 46968982 | D9: 46968462 | E9: 69085860 | F9: 69085095
A10: Y1/PL/TOI000 | B10: =VLOOKUP(A10,Sheet2!A:F,1+'P&L 2023.12'!C$1,FALSE) -> Operating income / loss | C10: 26634131 | D10: 26634131 | E10: 39181432 | F10: 39181432
A11: Y1/PL/T41000 | B11: =VLOOKUP(A11,Sheet2!A:F,1+'P&L 2023.12'!C$1,FALSE) -> Gross margin | C11: 1.549024e+08 | D11: 1.549024e+08 | E11: 2.2781272e+08 | F11: 2.2781272e+08
A12: Y1/PL/T41100 | B12: =VLOOKUP(A12,Sheet2!A:F,1+'P&L 2023.12'!C$1,FALSE) -> Revenue | C12: 2.4917317e+08 | D12: 2.4917317e+08 | E12: 3.6643401e+08 | F12: 3.6643401e+08
A13: 411100 | B13: =VLOOKUP(A13,Sheet2!A:F,1+'P&L 2023.12'!C$1,FALSE) -> Sale of goods | C13: 2.4917317e+08 | D13: 2.4917317e+08 | E13: 3.6643401e+08 | F13: 3.6643401e+08
A14: Y1/PL/T41200 | B14: =VLOOKUP(A14,Sheet2!A:F,1+'P&L 2023.12'!C$1,FALSE) -> Changes in Inventory / COS | C14: -94270769 | D14: -94270769 | E14: -1.3862129e+08 | F14: -1.3862129e+08
A15: 412100 | B15: =VLOOKUP(A15,Sheet2!A:F,1+'P&L 2023.12'!C$1,FALSE) -> Changes in Inventory | C15: -10949723 | D15: -10949723 | E15: -16089373 | F15: -16089373
A16: 412200 | B16: =VLOOKUP(A16,Sheet2!A:F,1+'P&L 2023.12'!C$1,FALSE) -> Cost of purchased services and materials | C16: -83321046 | D16: -83321046 | E16: -1.2253191e+08 | F16: -1.2253191e+08
A17: 41200D | B17: =VLOOKUP(A17,Sheet2!A:F,1+'P&L 2023.12'!C$1,FALSE) -> Clearing account - Gross margin | C17: 0 | D17: 0 | E17: 0 | F17: 0
A18: Y1/PL/T57000 | B18: =VLOOKUP(A18,Sheet2!A:F,1+'P&L 2023.12'!C$1,FALSE) -> Depreciation | C18: -30000 | D18: -30000 | E18: -44118 | F18: -44118
A19: 571000 | B19: =VLOOKUP(A19,Sheet2!A:F,1+'P&L 2023.12'!C$1,FALSE) -> Amort./depr./ impair. on fixed assets | C19: -30000 | D19: -30000 | E19: -44118 | F19: -44118
A20: Y1/PL/T51000 | B20: =VLOOKUP(A20,Sheet2!A:F,1+'P&L 2023.12'!C$1,FALSE) -> Other operating income | C20: 1953265.9 | D20: 1953265.9 | E20: 2872472.4 | F20: 2872472.4
A21: 511000 | B21: =VLOOKUP(A21,Sheet2!A:F,1+'P&L 2023.12'!C$1,FALSE) -> Gains on the disposal of PPE | C21: 1744709.9 | D21: 1744709.9 | E21: 2565770 | F21: 2565770
A22: 511200 | B22: =VLOOKUP(A22,Sheet2!A:F,1+'P&L 2023.12'!C$1,FALSE) -> Gains on the disposal of intangible assets | C22: 13654.06 | D22: 13654.06 | E22: 20079.65 | F22: 20079.65
A23: 511300 | B23: =VLOOKUP(A23,Sheet2!A:F,1+'P&L 2023.12'!C$1,FALSE) -> Gains on the disposal of other assets | C23: 10939.96 | D23: 10939.96 | E23: 16088.3 | F23: 16088.3
A24: 515000 | B24: =VLOOKUP(A24,Sheet2!A:F,1+'P&L 2023.12'!C$1,FALSE) -> Other operating income | C24: 183961.98 | D24: 183961.98 | E24: 270534.46 | F24: 270534.46
A25: Y1/PL/T58000 | B25: =VLOOKUP(A25,Sheet2!A:F,1+'P&L 2023.12'!C$1,FALSE) -> Other operating expenses | C25: -1.3019154e+08 | D25: -1.3019154e+08 | E25: -1.9145964e+08 | F25: -1.9145964e+08
A26: 584000 | B26: =VLOOKUP(A26,Sheet2!A:F,1+'P&L 2023.12'!C$1,FALSE) -> Accruals | C26: -134732.64 | D26: -134732.64 | E26: -198137.76 | F26: -198137.76
A27: 585000 | B27: =VLOOKUP(A27,Sheet2!A:F,1+'P&L 2023.12'!C$1,FALSE) -> Other operating expenses | C27: -1.300568e+08 | D27: -1.300568e+08 | E27: -1.9126151e+08 | F27: -1.9126151e+08
A28: 58000D | B28: =VLOOKUP(A28,Sheet2!A:F,1+'P&L 2023.12'!C$1,FALSE) -> Clearing account - Other operating | C28: 0 | D28: 0 | E28: -0.01 | F28: -0.01
A29: 651000 | B29: =VLOOKUP(A29,Sheet2!A:F,1+'P&L 2023.12'!C$1,FALSE) -> Allowances (reversals) for provisions on shares | C29: 0 | D29: 0 | E29: 0 | F29: 0
A30: Y1/PL/TIIL00 | B30: =VLOOKUP(A30,Sheet2!A:F,1+'P&L 2023.12'!C$1,FALSE) -> Investing Income / Loss | C30: 20334851 | D30: 20334331 | E30: 29904428 | F30: 29903663
A31: 511100 | B31: =VLOOKUP(A31,Sheet2!A:F,1+'P&L 2023.12'!C$1,FALSE) -> Gains on the disposal of investment property | C31: 19220955 | D31: 19220955 | E31: 28266332 | F31: 28266332
A32: 601000 | B32: =VLOOKUP(A32,Sheet2!A:F,1+'P&L 2023.12'!C$1,FALSE) -> Interest income | C32: 898112.87 | D32: 898112.87 | E32: 1320764.6 | F32: 1320764.6
A33: 603000 | B33: =VLOOKUP(A33,Sheet2!A:F,1+'P&L 2023.12'!C$1,FALSE) -> Dividends | C33: 185713.42 | D33: 185713.42 | E33: 273110.59 | F33: 273110.59
A34: 711000 | B34: =VLOOKUP(A34,Sheet2!A:F,1+'P&L 2023.12'!C$1,FALSE) -> Share of profit - associates / JV at equity method | C34: 30070.04 | D34: 29550.04 | E34: 44221 | F34: 43456.29
A35: Y1/PL/TFIL00 | B35: =VLOOKUP(A35,Sheet2!A:F,1+'P&L 2023.12'!C$1,FALSE) -> Financing Income / Loss | C35: -1035618.6 | D35: -1033017.6 | E35: -1522980.4 | F35: -1519155.4
A36: 602000 | B36: =VLOOKUP(A36,Sheet2!A:F,1+'P&L 2023.12'!C$1,FALSE) -> Financial fair value gains or losses | C36: 19888.12 | D36: 19888.12 | E36: 29247.47 | F36: 29247.47
A37: 604000 | B37: =VLOOKUP(A37,Sheet2!A:F,1+'P&L 2023.12'!C$1,FALSE) -> Other financial income | C37: 564307.44 | D37: 564307.44 | E37: 829870.37 | F37: 829870.37
A38: 652000 | B38: =VLOOKUP(A38,Sheet2!A:F,1+'P&L 2023.12'!C$1,FALSE) -> Interest expenses | C38: -62705.42 | D38: -62705.42 | E38: -92214.57 | F38: -92214.57
A39: 653000 | B39: =VLOOKUP(A39,Sheet2!A:F,1+'P&L 2023.12'!C$1,FALSE) -> Other financial expenses | C39: -1557108.7 | D39: -1554507.7 | E39: -2289883.7 | F39: -2286058.7
A40: 65400D | B40: =VLOOKUP(A40,Sheet2!A:F,1+'P&L 2023.12'!C$1,FALSE) -> Clearing account - financial result | C40: 0 | D40: 0 | E40: 0.01 | F40: 0.01
A41: Y1/PL/T72000 | B41: =VLOOKUP(A41,Sheet2!A:F,1+'P&L 2023.12'!C$1,FALSE) -> Tax | C41: -11049256 | D41: -11049256 | E41: -16249033 | F41: -16249033
A42: 721000 | B42: =VLOOKUP(A42,Sheet2!A:F,1+'P&L 2023.12'!C$1,FALSE) -> Income tax | C42: -11151789 | D42: -11151789 | E42: -16399818 | F42: -16399818
A43: 722000 | B43: =VLOOKUP(A43,Sheet2!A:F,1+'P&L 2023.12'!C$1,FALSE) -> Deferred tax | C43: 102532.87 | D43: 102532.87 | E43: 150784.85 | F43: 150784.85
A44: Y1/PL/T73000 | B44: =VLOOKUP(A44,Sheet2!A:F,1+'P&L 2023.12'!C$1,FALSE) -> Profit (loss) from discontinued operations | C44: -152691.49 | D44: -152691.49 | E44: -224548.1 | F44: -224548.1
A45: 730000 | B45: =VLOOKUP(A45,Sheet2!A:F,1+'P&L 2023.12'!C$1,FALSE) -> Profit (loss) from discontinued operations | C45: -152691.49 | D45: -152691.49 | E45: -224548.1 | F45: -224548.1
A46: 792000 | B46: =VLOOKUP(A46,Sheet2!A:F,1+'P&L 2023.12'!C$1,FALSE) -> Net income - NCI | C46: -12640810 | D46: -12641070 | E46: -18592075 | F46: -18592457
A47: REST_H | B47: =VLOOKUP(A47,Sheet2!A:F,1+'P&L 2023.12'!C$1,FALSE) -> Not Assigned FS Item (s) | C47: 733989.21 | D47: 733989.21 | E47: 1021492.9 | F47: 1021492.9

Sheet Sheet2
B1: I_TXTMI_EN | C1: I_TXTMI_DE | D1: I_TXTMI_JA | E1: I_TXTMI_PT | F1: I_TXTMI_ZH
A2: 0 | B2: Control | C2: Steuern | D2: コントロール | E2: Ao controle
A3: 1 | B3: Control 1 | C3: Steuern 1 | D3: コントロール 1 | E3: Ao controle 1
A4: 2 | B4: Control 2 | C4: Steuern 2 | D4: コントロール 2 | E4: Ao controle 2
A5: 3 | B5: Control 3 | C5: Steuern 3 | D5: コントロール 3 | E5: Ao controle 3
A6: 111100 | B6: Cash on hand | C6: Kassenbestand | D6: 手許現金 | E6: Ativo em caixa | F6: 库存现金
A7: 111200 | B7: Short-term deposits and other cash equivalents | C7: Kurzfr. Einlagen und andere Zahlungsmitteläquiv. | D7: 短期預金およびその他現金同等物 | E7: Depósitos a curto prazo e outros recursos líquidos | F7: 短期存款及其他现金等价物
A8: 121100 | B8: Trade receivables, Gross | C8: Forderungen aus Lieferungen und Leistungen, brutto | D8: 売上債権、総額 | E8: Créditos comerciais, bruto | F8: 贸易应收账款，总额
A9: 121190 | B9: Trade receivables, Allowance | C9: Forderungen aus Lief. und Leist., Wertberichtigung | D9: 売上債権、引当金 | E9: Créditos comerciais, ajuste de valor | F9: 贸易应收账款，补贴
A10: 121200 | B10: Receivables on disposal of PPE, Current, Gross | C10: Ford. aus Abgang von Sachanlagen, kurzfr., brutto | D10: PPE 処分の流動債権、総額 | E10: Créds.em alienação bem mat., curto prazo, bruto | F10: 物业、工厂与设备处置流动应收账款总额
A11: 121300 | B11: Receivables / disp. Intang.assets, Current, Gross | C11: Ford. aus Abgang imm. VermGgnst., kurzfr., brutto | D11: 無形資産の流動債権/処分、総額 | E11: Créds./alienação bens intangs., curto prz., bruto | F11: 无形资产处置应收账款的流动总额
A12: 121400 | B12: Receivables / disp. invest. subsid, Current, Gross | C12: Ford. aus Abgang Beteil. Tochter, kurzfr., brutto | D12: 子会社への投資の流動債権/処分、総額 | E12: Créds./alienação subsid.invest., curto prz., bruto | F12: 子公司投资处置应收账款的流动总额
A13: 121500 | B13: Receivables / disp. Inv. oth entities, Current, GV | C13: Ford. aus Abgang Beteil. an so. Einh., kurzfr., BW | D13: その他エンティティへの投資の流動債権/処分、GV | E13: Créds./alien.inv.outs.entds., curto prazo, bruto | F13: 其他实体投资处置应收账款的流动总价值
A14: 121600 | B14: Receivables /disp. Inv. oth assets, Current, Gross | C14: Ford. aus Abgang Btlg so. VermW., kurzfr., brutto | D14: その他資産への投資の流動債権/処分、総額 | E14: Créds./alien.inv.outros imobs., curto prazo, bruto | F14: 其他资产投资处置应收账款的流动总额
A15: 121700 | B15: Dividends receivable | C15: Dividendenforderung | D15: 未収配当金 | E15: Dividendos a receber | F15: 应收股利
A16: 121800 | B16: Other receivables, Current, Gross | C16: Sonstige Forderungen, kurzfristig, brutto | D16: その他流動債権、総額 | E16: Outros créditos, curto prazo, bruto | F16: 其他流动应收账款总额
A17: 121900 | B17: Accrued interests on receivables | C17: Aufgelaufene Zinsen auf Forderungen | D17: 債権の見越利息 | E17: Juros acumulados sobre créditos | F17: 应收账款的应计利息
... A217: 799999 | B217: Secondary cost element | C217: Sekundärkostenart | D217: 二次原価要素 | E217: Classe de custo secundário | F217: 次要成本要素
A218: 13100D | B218: Clearing Account - Gross Margin B/S | C218: Verrekeningsrekening - balans brutomarge | D218: 消込勘定 - 粗利益 B/S | E218: Conta compensação - margem bruta balanço | F218: 清账科目 - 总利润率资产负债表
A219: 14100D | B219: Clearing account - Financial assets, Current | C219: Verrechnungskonto - Fin. Vermögenswerte, kurzfr. | D219: 消込勘定 - 流動金融資産 | E219: Cta.compensação - imobilizados financeiros, CP | F219: 清账科目 - 流动金融资产
A220: 16100D | B220: Clearing account - Property, plant and equipment | C220: Verrechnungskonto - Sachanlagen | D220: 消込勘定 - 有形固定資産 | E220: Conta de compensação - bem material | F220: 清账科目 - 物业、工厂和设备
A221: 16200D | B221: Clearing account - Investment property | C221: Verrechnungskonto - Als Finanzinvest. geh. Immob. | D221: 消込勘定 - 投資不動産 | E221: Conta compensação - propriedade investimento | F221: 清账科目 - 投资财产
A222: 16300D | B222: Clearing account - Bargain purchase | C222: Verrechnungskonto - Erwerb unter dem Marktwert | D222: 消込勘定 - バーゲンパーチェス | E222: Conta compensação - compra favorável | F222: 清账科目 - 折价购买
A223: 16400D | B223: Clearing account - Intangible assets | C223: Verrechnungskonto - Immat. Vermögensgegenstände | D223: 消込勘定 - 無形資産 | E223: Conta de compensação - imobilizados intangíveis | F223: 清账科目 - 无形资产
A224: 17210D | B224: Clearing account - Investments in subs, JV, assoc. | C224: VerrechKto - Beteil. an Tochterges., JV, ass. Unt. | D224: 消込勘定 - 子会社、JV および関連会社への投資 | E224: Conta compensação - invs.subs., JV, empr.assocs. | F224: 清账科目 - 子公司、合资企业、附属公司投资
A225: 1721HC | B225: Elimination of investment, held cons unit | C225: Beteiligungseliminierung, gehaltene KonsEinheit | D225: 投資の消去、被保有連結単位 | E225: Eliminação investimento, unid.consolidação prev. | F225: 投资抵销，持有消耗单元
A226: 1721OC | B226: Elimination of investment, owner cons unit | C226: Beteiligungseliminierung, Eigentümer KonsEinheit | D226: 投資の消去、所有者連結単位 | E226: Eliminação investimento, propr.unid.consolidação | F226: 投资抵销，所有者消耗单元
A227: 17220D | B227: Clearing account - Financial assets, Non-current | C227: Verrechnungskonto - Fin. Vermögenswerte, langfr. | D227: 消込勘定 - 非流動金融資産 | E227: Conta compensação - imobs.financeiros, longo prazo | F227: 清账科目 - 非流动金融资产
A228: 19900D | B228: Balancing account - B/S | C228: Ausgleichskonto - Bilanz | D228: 残高調整勘定 - B/S | E228: Conta de compensação - balanço | F228: 结算科目 - 资产负债表
A229: 21100D | B229: Clearing account - Receivables/payables, Current | C229: Verrechnungskonto - Ford./Verbindl., kurzfristig | D229: 消込勘定 - 流動債権/債務 | E229: Conta compensação - créds./obrigações, curto prazo | F229: 清账科目 - 流动应收账款/应付账款
... A246: AA | B246: Group share | C246: Konzernanteil | D246: グループシェア | E246: Compartilhamento de grupo | F246: Group share
A247: AAA | B247: Correction | C247: Korrektur | D247: 補正 | E247: Correção
A248: B | B248: Total liabilities | C248: Gesamtverbindlichkeiten | D248: 総負債 | E248: Resposabilidades totais | F248: 总负债
A249: BBB | B249: Cloud Consolidation | C249: Cloud-Konsolidierung | D249: クラウドの統合 | E249: Consolidação de nuvem
A250: BS | B250: Balance Sheet | C250: Bilanz | D250: 貸借対照表 | E250: Balanço | F250: 资产负债表
A251: C | B251: Total equity | C251: Gesamtkapital | D251: 総資本 | E251: Patrimônio total | F251: 总资本
A252: D | B252: Net income | C252: Nettoeinkommen | D252: 当期純利益 | E252: Resultado líquido | F252: 净收入
A253: E | B253: Amount in Group Crcy | C253: Bedrag concernvaluta | D253: グループ通貨額 | E253: Montante MGE | F253: 集团公司记帐货币
A254: F | B254: Sign-Adjusted Amount in Group Crcy | C254: Betrag mit angepasstem Vorzeichen in KW | D254: 符号調整済金額 (連結通貨) | E254: Montante c/sinal ajustado em MGC | F254: 以集团货币计的符号已调整金额
A255: Financial Statement Item | B255: Medium Text for FS Items | C255: Medium Text for FS Items | D255: Medium Text for FS Items | E255: Medium Text for FS Items | F255: Medium Text for FS Items
A256: IPI_GV_M | B256: IPI-Internal Inventory Gross Value-Merchandise | C256: IPI - Interner Bestand Bruttowert - Waren | D256: IPI - 社内棚卸資産総額 - 商品 | E256: IPI-valor bruto estoque interno-mercadorias | F256: IPI - 内部库存总价值 - 商品
A257: IPI_RATE | B257: IPI-Margin Rate (%) | C257: IPI - Margensatz (%) | D257: IPI - 利益率 (%) | E257: IPI-taxa margem (%) | F257: IPI - 毛利率 (%)
A258: PL | B258: Profit and loss | C258: Gewinn und Verlust | D258: 収益と損失 | E258: Lucros e perdas | F258: 损益
A259: PL | B259: BS and PL | C259: Bilanz und GuV | D259: BS および PL | E259: Balanço e DRE | F259: 损益
A260: REST_H | B260: Not Assigned FS Item (s) | C260: Nicht zug. Position(n/e) | D260: 未割当 連結勘定科目 | E260: Não atrib. Item(s) | F260: 未分配 财务报表项目 (s)
A261: S00001 | B261: Group Shares (%) | C261: Kreisanteile (%) | D261: グループ持分 (%) | E261: Participações do grupo (%) | F261: 集团股份 (%)
... A436: X12002 | B436: Net value investment in subs.JV and associates | C436: Nettowert Beteiligung an Tocht., JV und ass. Unt. | D436: 子会社、JV および関連会社への投資正味額 | E436: Investimento val.líq.em JV subsid.e emprs.assocs. | F436: 子公司、合资企业和附属公司中的净值投资
A437: X13000 | B437: Interunit Elimination | C437: Konzernaufrechnung | D437: 内部取引消去 | E437: Eliminações de consolidação
A438: X13001 | B438: PL IC OP income | C438: GuV - interne betriebliche Erträge | D438: 損益会社間営業収益 | E438: Resultado operacional IE
A439: X13002 | B439: PL IC Expense 1 | C439: GuV - interner Aufwand 1 | D439: 損益会社間費用 1 | E439: Resultado despesa IE 1
A440: X13003 | B440: PL IC Financial inc | C440: GuV - interne Finanzerträge | D440: PL IC 財務収益 | E440: Resultado rendimento financeiro IE
A441: X13004 | B441: PL IC Financial exp | C441: GuV - interne Finanzaufwendungen | D441: PL IC 財務費用 | E441: Resultado despesas financeiras IE
A442: X13005 | B442: Sale of goods | C442: Verkauf von Gütern | D442: 商品販売 | E442: Venda de mercadorias
A443: X13006 | B443: Rendering services | C443: Erbringung von Dienstleistungen | D443: 実施サービス | E443: Prestação de serviços
A444: X13007 | B444: IC Trade Receivable | C444: Intern - Forderungen aus Lief. u. Leist. | D444: 会社間売上債権 | E444: Créditos comerciais IE
A445: X13008 | B445: IC Trade Payables | C445: Intern - Verbindlichkeiten aus LuL | D445: 会社間支払債務 | E445: Obrigações comerciais IE
A446: X13009 | B446: IC Other Rec Current | C446: Intern - sonstige Forderungen, kurzfristig | D446: IC その他流動債権 | E446: Outros créditos IE curto prazo
A447: X13010 | B447: IC Other Liab Current | C447: Intern - sonstige Verbindlichkeiten, kurzfristig | D447: IC その他流動負債 | E447: Outras obrigações IE curto prazo
A448: X13011 | B448: BS Dividends Receivables | C448: Bilanz - Forderungen aus Dividenden | D448: 貸借対照表未収配当金 | E448: Balanço de dividendos a receber
... A491: X14118 | B491: Income tax on recyclable fair value reserve | C491: Ertragsteuer auf wiederverwendb. Zeitwertrücklage | D491: 再利用時価準備金の所得税 | E491: Imposto renda sobre reserva val.atual reutilizável
A492: X15000 | B492: X15000 | C492: X15000 | D492: X15000 | E492: X15000 | F492: X15000
A493: X19000 | B493: Balancing Accounts | C493: Ausgleichskonten | D493: 残高調整勘定 | E493: Contas de compensação | F493: 结算科目
A494: X2/X2 | B494: Statement of Cash Flow | C494: Kapitalflussrechnung | D494: キャッシュフロー計算書 | E494: Demonstração do fluxo de caixa | F494: 现金流报表
A495: X90000 | B495: X90000 | C495: X90000 | D495: X90000 | E495: X90000 | F495: X90000
A496: X99999 | B496: X99999 | C496: X99999 | D496: X99999 | E496: X99999 | F496: X99999
A497: Y1/BS/BS | B497: Balance Sheet | C497: Bilanz | D497: 貸借対照表 | E497: Balanço | F497: 资产负债表
A498: Y1/BS/T11100 | B498: Cash and cash equivalents | C498: Zahlungsmittel und Zahlungsmitteläquivalente | D498: 現金および現金同等物 | E498: Recursos líquidos | F498: 现金和现金等价物
A499: Y1/BS/T12100 | B499: Trade and other current receivables | C499: Forderungen aus LuL und andere kurzfristige Ford. | D499: 売上債権およびその他流動債権 | E499: Créditos comerciais e outros a curto prazo | F499: 贸易和其他流动应收账款
A500: Y1/BS/T12200 | B500: Current tax assets | C500: Kurzfristige Steueransprüche | D500: 流動税金資産 | E500: Ativos de imposto a curto prazo | F500: 流动税资产
A501: Y1/BS/T12300 | B501: Other current assets | C501: Sonstiges Umlaufvermögen | D501: その他流動資産 | E501: Outro ativo circulante | F501: 其他流动资产
A502: Y1/BS/T13100 | B502: Inventories | C502: Vorräte | D502: 棚卸資産 | E502: Estoques | F502: 库存
A503: Y1/BS/T14100 | B503: Other current financial assets | C503: Sonstige kurzfristige finanzielle Vermögenswerte | D503: その他流動金融資産 | E503: Outros imobilizados financeiros a curto prazo | F503: 其他流动金融资产
... A566: Y1/PL/TOI000 | B566: Operating income / loss | C566: Betriebsergebnis | D566: 営業損益 | E566: Resultado/perda operacional | F566: 营业收入/损失
